{
  "slug": "personas/validar/evaluarpae",
  "pageTitle": "Evaluar PAE",
  "description": "Método para retornar el resultado de evaluar el PAE de una persona.",
  "pubName": "BTPersonas.EvaluarPAE",
  "programa": "RBTPGP50",
  "scope": "Global",
  "hasBackendConfig": false,
  "backendText": "",
  "backendData": [],
  "inputData": [
    {
      "Nombre": "modeloId",
      "Tipo": "Int",
      "Comentarios": "Identificador del modelo."
    },
    {
      "Nombre": "personaUId",
      "Tipo": "Long",
      "Comentarios": "Identificador único de persona."
    },
    {
      "Nombre": "productoUId",
      "Tipo": "Long",
      "Comentarios": "Identificador único del producto."
    },
    {
      "Nombre": "sdtValores",
      "Tipo": "sBTPAEValorItem",
      "Comentarios": "Colección de valores PAE."
    }
  ],
  "outputData": [
    {
      "Nombre": "valor",
      "Tipo": "Double",
      "Comentarios": "Valor."
    },
    {
      "Nombre": "mensaje",
      "Tipo": "String",
      "Comentarios": "Mensaje."
    },
    {
      "Nombre": "sdtPoliticas",
      "Tipo": "sBTPoliticaIncumplida",
      "Comentarios": "Colección de políticas incumplidas."
    },
    {
      "Nombre": "numeroEjecucion",
      "Tipo": "Long",
      "Comentarios": "Número de la ejecución."
    }
  ],
  "errors": [
    {
      "Código": "1011050",
      "Descripción": "No se recibió modelo de evaluación PAE."
    },
    {
      "Código": "1011051",
      "Descripción": "No se recuperó la persona para el Id recibido."
    },
    {
      "Código": "1011052",
      "Descripción": "No se recuperó el producto para el Id recibido."
    },
    {
      "Código": "1011053",
      "Descripción": "El modelo de evaluación no está definido."
    },
    {
      "Código": "1011054",
      "Descripción": "El modelo de evaluación no tiene tipo definido."
    },
    {
      "Código": "1011055",
      "Descripción": "No hay ítems a resolver para la evaluación solicitada."
    },
    {
      "Código": "1011056",
      "Descripción": "No es posible evaluar reglas en la plataforma de ejecución."
    },
    {
      "Código": "1011056",
      "Descripción": "Error en la parametrización del modelo de evaluación."
    },
    {
      "Código": "1011057",
      "Descripción": "Error en la ejecución del modelo de evaluación."
    }
  ],
  "examples": {
    "invocation": {
      "xml": "<soapenv:Envelope xmlns:soapenv=\"http://schemas.xmlsoap.org/soap/envelope/\" xmlns:bts=\"http://uy.com.dlya.bantotal/BTSOA/\">\n   <soapenv:Header/>\n   <soapenv:Body>\n      <bts:BTPersonas.EvaluarPAE>\n         <bts:Btinreq>\n            <bts:Requerimiento>0</bts:Requerimiento>\n            <bts:Canal>BTDIGITAL</bts:Canal>\n            <bts:Device>GZ</bts:Device>\n            <bts:Usuario>INSTALADOR</bts:Usuario>\n            <bts:Token>E1F15D391E5C8FAC4189A627</bts:Token>\n         </bts:Btinreq>\n         <bts:modeloId>23</bts:modeloId>\n         <bts:personaUId>62</bts:personaUId>\n         <bts:productoUId>3</bts:productoUId>\n         <bts:sdtValores>\n            <bts:sBTPAEValorItem>\n               <bts:itemValor></bts:itemValor>\n               <bts:itemNombre></bts:itemNombre>\n            </bts:sBTPAEValorItem>\n         </bts:sdtValores>\n      </bts:BTPersonas.EvaluarPAE>\n   </soapenv:Body>\n</soapenv:Envelope>",
      "json": "curl -X POST \\\n  'http://btd-bantotal.eastus2.cloudapp.azure.com:4462/btdeveloper/servlet/com.dlya.bantotal.odwsbt_BTPersonas_v1?EvaluarPAE=' \\\n  -H 'cache-control: no-cache' \\\n  -H 'content-type: application/json' \\\n  -H 'postman-token: 631e45d0-2c12-1ccc-7e5c-a067d4de5fb8' \\\n  -d '{\n\t\"Btinreq\": {\n\t\t\"Device\": \"GZ\",\n\t\t\"Usuario\": \"MINSTALADOR\",\n\t\t\"Requerimiento\": \"\",\n\t\t\"Canal\": \"BTDIGITAL\",\n\t\t\"Token\": \"fa2c02c95a4A8B5C60A82434\"\n\t},\n   \"modeloId\": 23,\n   \"personaUId\": 62,\n   \"productoUId\": 3,\n   \"sdtValores\": {\n      \"sBTPAEValorItem\": {\n      \"itemValor\": \"\",\n      \"itemNombre\": \"\"\n      }\n   }\n}'"
    },
    "response": {
      "xml": "<SOAP-ENV:Envelope xmlns:SOAP-ENV=\"http://schemas.xmlsoap.org/soap/envelope/\" xmlns:xsd=\"http://www.w3.org/2001/XMLSchema\" xmlns:SOAP-ENC=\"http://schemas.xmlsoap.org/soap/encoding/\" xmlns:xsi=\"http://www.w3.org/2001/XMLSchema-instance\">\n   <SOAP-ENV:Body>\n      <BTPersonas.EvaluarPAEResponse xmlns=\"http://uy.com.dlya.bantotal/BTSOA/\">\n         <Btinreq>\n            <Device>GZ</Device>\n            <Usuario>INSTALADOR</Usuario>\n            <Requerimiento>0</Requerimiento>\n            <Canal>BTDIGITAL</Canal>\n            <Token>E1F15D391E5C8FAC4189A627</Token>\n         </Btinreq>\n         <valor>10000.0</valor>\n         <mensaje/>\n         <sdtPoliticas/>\n         <numeroEjecucion>2</numeroEjecucion>\n         <Erroresnegocio></Erroresnegocio>\n         <Btoutreq>\n            <Numero>16893</Numero>\n            <Estado>OK</Estado>\n            <Servicio>BTPersonas.EvaluarPAE</Servicio>\n            <Requerimiento>0</Requerimiento>\n            <Fecha>2023-10-31</Fecha>\n            <Hora>08:50:51</Hora>\n            <Canal>BTDIGITAL</Canal>\n         </Btoutreq>\n      </BTPersonas.EvaluarPAEResponse>\n   </SOAP-ENV:Body>\n</SOAP-ENV:Envelope>",
      "json": "{\n\t\"Btinreq\": {\n\t\t\"Device\": \"AV\",\n\t\t\"Usuario\": \"MINSTALADOR\",\n\t\t\"Requerimiento\": \"\",\n\t\t\"Canal\": \"BTDIGITAL\",\n\t\t\"Token\": \"fa2c02c95a4A8B5C60A82434\"\n\t},\n   \"valor\": 10000,\n   \"mensaje\": {},\n   \"sdtPoliticas\": {},\n   \"numeroEjecucion\": 2,\n   \"Erroresnegocio\": {\n       \"BTErrorNegocio\": []\n   },\n   \"Btoutreq\": {\n       \"Numero\": \"835\",\n       \"Estado\": \"OK\",\n       \"Servicio\": \"BTPersonas.EvaluarPAE\",\n       \"Fecha\": \"2017-12-18\",\n       \"Requerimiento\": \"\",\n       \"Hora\": \"01:48:53\",\n       \"Canal\": \"BTDIGITAL\"\n   }\n}"
    }
  },
  "structuredTypes": [
    {
      "typeName": "sBTPAEValorItem",
      "fields": [
        {
          "Nombre": "itemNombre",
          "Tipo": "String",
          "Comentarios": "Nombre del ítem."
        },
        {
          "Nombre": "itemValor",
          "Tipo": "String",
          "Comentarios": "Valor del ítem."
        }
      ]
    },
    {
      "typeName": "sBTPoliticaIncumplida",
      "fields": [
        {
          "Nombre": "estado",
          "Tipo": "String",
          "Comentarios": "Estado."
        },
        {
          "Nombre": "estadoDsc",
          "Tipo": "String",
          "Comentarios": "Descripción del estado."
        },
        {
          "Nombre": "nroAutorizacion",
          "Tipo": "Long",
          "Comentarios": "Número de la autorización."
        },
        {
          "Nombre": "observacion",
          "Tipo": "String",
          "Comentarios": "Observación."
        },
        {
          "Nombre": "politica",
          "Tipo": "String",
          "Comentarios": "Política."
        },
        {
          "Nombre": "politicaId",
          "Tipo": "Int",
          "Comentarios": "Identificador de la política."
        },
        {
          "Nombre": "restriccion",
          "Tipo": "String",
          "Comentarios": "Restricción."
        },
        {
          "Nombre": "restriccionDsc",
          "Tipo": "String",
          "Comentarios": "Descripción de la restricción."
        }
      ]
    }
  ],
  "valuesTable": []
}