{
  "slug": "seguros-voluntarios/pagarseguro",
  "pageTitle": "Pagar Seguro",
  "description": "Método para pagar un seguro.",
  "pubName": "BTSegurosVoluntarios.PagarSeguro",
  "programa": "RBTPG545",
  "scope": "Global",
  "hasBackendConfig": false,
  "backendText": "",
  "backendData": [],
  "inputData": [
    {
      "Nombre": "seguroUId",
      "Tipo": "Long",
      "Comentarios": "Identificador único del seguro."
    },
    {
      "Nombre": "montoPago",
      "Tipo": "Double",
      "Comentarios": "Monto a pagar."
    },
    {
      "Nombre": "operacionUIdCobro",
      "Tipo": "Long",
      "Comentarios": "Identificador único de la operación de cobro."
    }
  ],
  "outputData": [
    {
      "Nombre": "movimientoUId",
      "Tipo": "long",
      "Comentarios": "Identificador único del movimiento."
    }
  ],
  "errors": [
    {
      "Código": "30002",
      "Descripción": "No se recibió el identificador de operación del seguro."
    },
    {
      "Código": "30003",
      "Descripción": "Se debe ingresar un monto."
    },
    {
      "Código": "30004",
      "Descripción": "No se recuperó la clave de operación para el identificador del seguro: [Número de Identificador]."
    },
    {
      "Código": "30005",
      "Descripción": "No se recuperó la clave de operación de cobro para el identificador: [Número de Identificador]."
    },
    {
      "Código": "50002",
      "Descripción": "La operación no existe."
    },
    {
      "Código": "50003",
      "Descripción": "La operación de cobro no existe."
    },
    {
      "Código": "50005",
      "Descripción": "Atención: No se pudo obtener el numerador para la transacción."
    },
    {
      "Código": "50006",
      "Descripción": "La operación esta cancelada."
    },
    {
      "Código": "50008",
      "Descripción": "La operación de cobro esta cancelada."
    },
    {
      "Código": "50010",
      "Descripción": "El monto ingresado supera al monto total de la deuda."
    }
  ],
  "examples": {
    "invocation": {
      "xml": "<soapenv:Envelope xmlns:soapenv=\"http://schemas.xmlsoap.org/soap/envelope/\" xmlns:bts=\"http://uy.com.dlya.bantotal/BTSOA/\">\n   <soapenv:Header/>\n   <soapenv:Body>\n      <bts:BTSegurosVoluntarios.PagarSeguro>\n         <bts:Btinreq>\n            <bts:Requerimiento>0</bts:Requerimiento>\n            <bts:Canal>BTDIGITAL</bts:Canal>\n            <bts:Device>GZ</bts:Device>\n            <bts:Usuario>INSTALADOR</bts:Usuario>\n            <bts:Token>89B4F6D7BEFB0C7F653DB37A</bts:Token>\n         </bts:Btinreq>\n         <bts:seguroUId>286</bts:seguroUId>\n         <bts:montoPago>543</bts:montoPago>\n         <bts:operacionUIdCobro>22</bts:operacionUIdCobro>\n      </bts:BTSegurosVoluntarios.PagarSeguro>\n   </soapenv:Body>\n</soapenv:Envelope>",
      "json": "curl -X POST \\\n    'http://btd-bantotal.eastus2.cloudapp.azure.com:4462/btdeveloper/servlet/com.dlya.bantotal.odwsbt_BTSegurosVoluntarios?ObtenerSeguros' \\\n    -H 'cache-control: no-cache' \\\n    -H 'content-type: application/json' \\\n    -H 'postman-token: 52baf1dc-e302-90a6-0de1-24fa234c0379' \\\n    -d '{\n    \"Btinreq\": {\n        \"Requerimiento\": 0,\n        \"Canal\": \"BTDIGITAL\",\n        \"Device\": \"AC\",\n        \"Usuario\": \"Instalador\",\n        \"Token\": \"8e3a8ef2dd99865B3A2E76CF\"\n    },\n    \"seguroUId\": 286,\n    \"montoPago\": 543,\n    \"operacionUIdCobro\": 22\n}'"
    },
    "response": {
      "xml": "<SOAP-ENV:Envelope xmlns:SOAP-ENV=\"http://schemas.xmlsoap.org/soap/envelope/\" xmlns:xsd=\"http://www.w3.org/2001/XMLSchema\" xmlns:SOAP-ENC=\"http://schemas.xmlsoap.org/soap/encoding/\" xmlns:xsi=\"http://www.w3.org/2001/XMLSchema-instance\">\n   <SOAP-ENV:Body>\n      <BTSegurosVoluntarios.PagarSeguroResponse xmlns=\"http://uy.com.dlya.bantotal/BTSOA/\">\n         <Btinreq>\n            <Device>GZ</Device>\n            <Usuario>INSTALADOR</Usuario>\n            <Requerimiento>0</Requerimiento>\n            <Canal>BTDIGITAL</Canal>\n            <Token>89B4F6D7BEFB0C7F653DB37A</Token>\n         </Btinreq>\n         <movimientoUId>125</movimientoUId>\n         <Erroresnegocio></Erroresnegocio>\n         <Btoutreq>\n            <Numero>20473</Numero>\n            <Estado>OK</Estado>\n            <Servicio>BTSegurosVoluntarios.PagarSeguro</Servicio>\n            <Fecha>2024-05-14</Fecha>\n            <Requerimiento>0</Requerimiento>\n            <Hora>15:58:12</Hora>\n            <Canal>BTDIGITAL</Canal>\n         </Btoutreq>\n      </BTSegurosVoluntarios.PagarSeguroResponse>\n   </SOAP-ENV:Body>\n</SOAP-ENV:Envelope>",
      "json": "{\n    \"Btinreq\": {\n        \"Canal\": \"BTDIGITAL\",\n        \"Requerimiento\": \"\",\n        \"Usuario\": \"BANTOTAL\",\n        \"Token\": \"324915377F955E77534D3E02\",\n        \"Device\": \"AC\"\n    },\n    \"movimientoUId\": 125,\n    \"Erroresnegocio\": {\n        \"BTErrorNegocio\": []\n    },\n    \"Btoutreq\": {\n        \"Canal\": \"BTDIGITAL\",\n        \"Servicio\": \"BTSegurosVoluntarios.PagarSeguro\",\n        \"Fecha\": \"2019-11-19\",\n        \"Hora\": \"13:05:22\",\n        \"Requerimiento\": \"\",\n        \"Numero\": 6924,\n        \"Estado\": \"OK\"\n    }\n}"
    }
  },
  "structuredTypes": [],
  "valuesTable": []
}