{
  "slug": "tarjetas-de-debito/operar/asociarcuenta",
  "pageTitle": "Asociar Cuenta",
  "description": "Método para asociar una cuenta vista a una tarjeta de débito dada.",
  "pubName": "BTTarjetasDeDebito.AsociarCuenta",
  "programa": "RBTPG377",
  "scope": "Global",
  "hasBackendConfig": false,
  "backendText": "",
  "backendData": [],
  "inputData": [
    {
      "Nombre": "operacionUId",
      "Tipo": "Long",
      "Comentarios": "Identificador único de operación."
    },
    {
      "Nombre": "tarjetaUId",
      "Tipo": "Long",
      "Comentarios": "Identificador único de tarjeta de débito."
    }
  ],
  "outputData": [],
  "errors": [
    {
      "Código": "30001",
      "Descripción": "No se recibió el Identificador de tarjeta de débito."
    },
    {
      "Código": "30002",
      "Descripción": "No se recibió el Identificador de operación a asociar."
    }
  ],
  "errorsNote": "",
  "examples": {
    "invocation": {
      "xml": "<soapenv:Envelope xmlns:soapenv=\"http://schemas.xmlsoap.org/soap/envelope/\" xmlns:bts=\"http://uy.com.dlya.bantotal/BTSOA/\">\n   <soapenv:Header/>\n   <soapenv:Body>\n      <bts:BTTarjetasDeDebito.AsociarCuenta>\n         <bts:Btinreq>\n            <bts:Canal>BTDIGITAL</bts:Canal>\n            <bts:Requerimiento></bts:Requerimiento>\n            <bts:Usuario>INSTALADOR</bts:Usuario>\n            <bts:Token>1080548031CD285A89A23FBE</bts:Token>\n            <bts:Device></bts:Device>\n         </bts:Btinreq>\n         <bts:operacionUId>10</bts:operacionUId>\n         <bts:tarjetaUId>1</bts:tarjetaUId>\n      </bts:BTTarjetasDeDebito.AsociarCuenta>\n   </soapenv:Body>\n</soapenv:Envelope>",
      "json": "{\n    \"Btinreq\": {\n        \"Canal\": \"BTDIGITAL\",\n        \"Requerimiento\": \"\",\n        \"Usuario\": \"INSTALADOR\",\n        \"Token\": \"1518870407CD285A89A23FBE\",\n        \"Device\": \"\"\n    },\n\n    \"operacionUId\":\"10\",\n    \"tarjetaUId\"  :\"1\"\n}"
    },
    "response": {
      "xml": "<SOAP-ENV:Envelope xmlns:SOAP-ENV=\"http://schemas.xmlsoap.org/soap/envelope/\" xmlns:xsd=\"http://www.w3.org/2001/XMLSchema\" xmlns:SOAP-ENC=\"http://schemas.xmlsoap.org/soap/encoding/\" xmlns:xsi=\"http://www.w3.org/2001/XMLSchema-instance\">\n   <SOAP-ENV:Body>\n      <BTTarjetasDeDebito.AsociarCuentaResponse xmlns=\"http://uy.com.dlya.bantotal/BTSOA/\">\n         <Btinreq>\n            <Canal>BTDIGITAL</Canal>\n            <Requerimiento/>\n            <Usuario>INSTALADOR</Usuario>\n            <Token>1080548031CD285A89A23FBE</Token>\n            <Device/>\n         </Btinreq>\n         <Erroresnegocio></Erroresnegocio>\n         <Btoutreq>\n            <Canal>BTDIGITAL</Canal>\n            <Servicio>BTTarjetasDeDebito.AsociarCuenta</Servicio>\n            <Fecha>2021-10-29</Fecha>\n            <Hora>14:27:12</Hora>\n            <Requerimiento/>\n            <Numero>8451</Numero>\n            <Estado>OK</Estado>\n         </Btoutreq>\n      </BTTarjetasDeDebito.AsociarCuentaResponse>\n   </SOAP-ENV:Body>\n</SOAP-ENV:Envelope>",
      "json": "{\n    \"Btinreq\": {\n        \"Canal\": \"BTDIGITAL\",\n        \"Requerimiento\": \"\",\n        \"Usuario\": \"INSTALADOR\",\n        \"Token\": \"1518870407CD285A89A23FBE\",\n        \"Device\": \"\"\n    },\n    \"Erroresnegocio\": {\n        \"BTErrorNegocio\": []\n    },\n    \"Btoutreq\": {\n        \"Canal\": \"BTDIGITAL\",\n        \"Servicio\": \"BTTarjetasDeDebito.AsociarCuenta\",\n        \"Fecha\": \"2021-10-29\",\n        \"Hora\": \"13:37:58\",\n        \"Requerimiento\": \"\",\n        \"Numero\": 8449,\n        \"Estado\": \"OK\"\n    }\n}"
    }
  },
  "structuredTypes": [],
  "valuesTable": []
}