{
  "slug": "loans/getcustomerloans",
  "pageTitle": "Get Customer Loans",
  "description": "Método para obtener un listado de los préstamos de una contraparte.",
  "pubName": "PublicLoans.getCustomerLoans",
  "modulo": "Loans",
  "programa": "PublicAPI.BTLOPA0001",
  "scope": "Global",
  "method": "",
  "endpoint": "",
  "hasBackendConfig": false,
  "backendText": "",
  "backendData": [],
  "headersData": [],
  "headersNote": "",
  "inputNote": "",
  "inputData": [
    {
      "Nombre": "counterpartyGUID",
      "Tipo": "String <strong>(Length: 36)</strong>",
      "Comentarios": "GUID (identificador único global) de la contraparte."
    },
    {
      "Nombre": "cancelledLoans",
      "Tipo": "Boolean",
      "Comentarios": "Incluir préstamos cancelados."
    }
  ],
  "bodyNote": "",
  "bodyData": [],
  "outputNote": "",
  "outputData": [
    {
      "Nombre": "customerLoans",
      "Tipo": "<a href=\"#sdtsbtlowcustomerloan\">SdtsBTLOWCustomerLoan</a>",
      "Comentarios": "Listado de préstamos del cliente."
    }
  ],
  "errors": [
    {
      "Código": "40050100",
      "Descripción": "Debe ingresar el GUID de contraparte."
    }
  ],
  "errorsNote": "",
  "examples": {
    "invocation": {
      "json": "{\n  \"Btinreq\": {\n    \"Canal\": \"BTDIGITAL\",\n    \"Usuario\": \"INSTALADOR\",\n    \"Device\": \"INSTALADOR\",\n    \"Requerimiento\": \"1\",\n    \"Token\": \"444B674391BCA7676279700A\"\n  },\n  \"counterpartyGUID\": \"45399742-1326-4d8d-b7c8-10eb4cf976b0\",\n  \"cancelledLoans\": false\n}'",
      "xml": "",
      "tabs": [
        {
          "name": "JSON",
          "lang": "json",
          "code": "{\n  \"Btinreq\": {\n    \"Canal\": \"BTDIGITAL\",\n    \"Usuario\": \"INSTALADOR\",\n    \"Device\": \"INSTALADOR\",\n    \"Requerimiento\": \"1\",\n    \"Token\": \"444B674391BCA7676279700A\"\n  },\n  \"counterpartyGUID\": \"45399742-1326-4d8d-b7c8-10eb4cf976b0\",\n  \"cancelledLoans\": false\n}'"
        }
      ]
    },
    "response": {
      "json": "{\n  \"Btinreq\": {\n    \"Canal\": \"BTDIGITAL\",\n    \"Usuario\": \"INSTALADOR\",\n    \"Device\": \"INSTALADOR\",\n    \"Requerimiento\": \"1\",\n    \"Token\": \"TOKEN_AQUI\"\n  },\n  \"customerLoans\": {\n    \"customerLoan\": [\n      {\n        \"AmortizationTypeDescription\": \"AMORTIZABLE FRANCÉS (CONSTANTE TOTAL)\",\n        \"AmortizationTypeId\": 3,\n        \"Product\": {\n          \"ProductGUID\": \"d6328022-6f93-4afc-b59b-a29f435aba41\",\n          \"CurrencyDescription\": \"Pesos Uruguayos\",\n          \"KindDescription\": \"Billete\",\n          \"CurrencySign\": \"$\",\n          \"KindId\": 0,\n          \"ProductDescription\": \"COMPRA DE VIVIENDA\",\n          \"CurrencyId\": 0\n        },\n        \"Term\": 699,\n        \"BranchId\": 1,\n        \"OriginalAmount\": 100000,\n        \"NumberOfInstallments\": 24,\n        \"InstallmentPeriodicity\": 30,\n        \"TotalPaidInstallments\": 0,\n        \"InstallmentValue\": 5544.14,\n        \"ExpirationDate\": \"2026-12-08\",\n        \"FirstUnpaidDate\": \"2025-01-08\",\n        \"StatusDescription\": \"Normal\",\n        \"AccountBalance\": -100000,\n        \"ValueDate\": \"2025-01-08\",\n        \"StatusId\": 0,\n        \"LoanGUID\": \"d59d0a0b-ff0e-4264-a425-c8dc87027c0a\",\n        \"InterestRate\": 23,\n        \"BranchDescription\": \"Sucursal Beta\"\n      },\n      {\n        \"AmortizationTypeDescription\": \"AMORTIZABLE FRANCÉS (CONSTANTE TOTAL)\",\n        \"AmortizationTypeId\": 3,\n        \"Product\": {\n          \"ProductGUID\": \"d6328022-6f93-4afc-b59b-a29f435aba41\",\n          \"CurrencyDescription\": \"Pesos Uruguayos\",\n          \"KindDescription\": \"Billete\",\n          \"CurrencySign\": \"$\",\n          \"KindId\": 0,\n          \"ProductDescription\": \"COMPRA DE VIVIENDA\",\n          \"CurrencyId\": 0\n        },\n        \"Term\": 1795,\n        \"BranchId\": 1,\n        \"OriginalAmount\": 100000,\n        \"NumberOfInstallments\": 60,\n        \"InstallmentPeriodicity\": 30,\n        \"TotalPaidInstallments\": 0,\n        \"InstallmentValue\": 3203.86,\n        \"ExpirationDate\": \"2030-07-08\",\n        \"FirstUnpaidDate\": \"2027-05-10\",\n        \"StatusDescription\": \"Normal\",\n        \"AccountBalance\": -100000,\n        \"ValueDate\": \"2025-08-08\",\n        \"StatusId\": 0,\n        \"LoanGUID\": \"ceec5783-b363-4263-afe6-62387c8f72d8\",\n        \"InterestRate\": 23,\n        \"BranchDescription\": \"Sucursal Beta\"\n      },\n      {\n        \"AmortizationTypeDescription\": \"AMORTIZABLE FRANCÉS (CONSTANTE TOTAL)\",\n        \"AmortizationTypeId\": 3,\n        \"Product\": {\n          \"ProductGUID\": \"d6328022-6f93-4afc-b59b-a29f435aba41\",\n          \"CurrencyDescription\": \"Pesos Uruguayos\",\n          \"KindDescription\": \"Billete\",\n          \"CurrencySign\": \"$\",\n          \"KindId\": 0,\n          \"ProductDescription\": \"COMPRA DE VIVIENDA\",\n          \"CurrencyId\": 0\n        },\n        \"Term\": 347,\n        \"BranchId\": 1,\n        \"OriginalAmount\": 100000,\n        \"NumberOfInstallments\": 12,\n        \"InstallmentPeriodicity\": 30,\n        \"TotalPaidInstallments\": 0,\n        \"InstallmentValue\": 9703.77,\n        \"ExpirationDate\": \"2028-02-08\",\n        \"FirstUnpaidDate\": \"2027-04-08\",\n        \"StatusDescription\": \"Normal\",\n        \"AccountBalance\": -100000,\n        \"ValueDate\": \"2027-02-26\",\n        \"StatusId\": 0,\n        \"LoanGUID\": \"973d2029-da60-45f2-9edc-7feede4e4933\",\n        \"InterestRate\": 23,\n        \"BranchDescription\": \"Sucursal Beta\"\n      },\n      {\n        \"AmortizationTypeDescription\": \"AMORTIZABLE FRANCÉS (CONSTANTE TOTAL)\",\n        \"AmortizationTypeId\": 3,\n        \"Product\": {\n          \"ProductGUID\": \"b28af066-a6af-4ad5-9ad6-bfc925f93eee\",\n          \"CurrencyDescription\": \"Pesos Uruguayos\",\n          \"KindDescription\": \"Billete\",\n          \"CurrencySign\": \"$\",\n          \"KindId\": 0,\n          \"ProductDescription\": \"REFACCIÓN DE VIVIENDA\",\n          \"CurrencyId\": 0\n        },\n        \"Term\": 360,\n        \"BranchId\": 90,\n        \"OriginalAmount\": 100000,\n        \"NumberOfInstallments\": 12,\n        \"InstallmentPeriodicity\": 30,\n        \"TotalPaidInstallments\": 0,\n        \"InstallmentValue\": 11117.26,\n        \"ExpirationDate\": \"2028-06-08\",\n        \"FirstUnpaidDate\": \"2027-07-08\",\n        \"StatusDescription\": \"Normal\",\n        \"AccountBalance\": -100000,\n        \"ValueDate\": \"2027-06-14\",\n        \"StatusId\": 0,\n        \"LoanGUID\": \"83cc0e94-5115-482b-aeb9-0934a38e5905\",\n        \"InterestRate\": 23,\n        \"BranchDescription\": \"TESORERIA\"\n      },\n      {\n        \"AmortizationTypeDescription\": \"AMORTIZABLE FRANCÉS (CONSTANTE TOTAL)\",\n        \"AmortizationTypeId\": 3,\n        \"Product\": {\n          \"ProductGUID\": \"b28af066-a6af-4ad5-9ad6-bfc925f93eee\",\n          \"CurrencyDescription\": \"Pesos Uruguayos\",\n          \"KindDescription\": \"Billete\",\n          \"CurrencySign\": \"$\",\n          \"KindId\": 0,\n          \"ProductDescription\": \"REFACCIÓN DE VIVIENDA\",\n          \"CurrencyId\": 0\n        },\n        \"Term\": 360,\n        \"BranchId\": 90,\n        \"OriginalAmount\": 100000,\n        \"NumberOfInstallments\": 12,\n        \"InstallmentPeriodicity\": 30,\n        \"TotalPaidInstallments\": 0,\n        \"InstallmentValue\": 11117.26,\n        \"ExpirationDate\": \"2028-06-08\",\n        \"FirstUnpaidDate\": \"2027-07-08\",\n        \"StatusDescription\": \"Normal\",\n        \"AccountBalance\": -100000,\n        \"ValueDate\": \"2027-06-14\",\n        \"StatusId\": 0,\n        \"LoanGUID\": \"bdde1d9a-bdd5-4490-a3e4-02de8d7f35e7\",\n        \"InterestRate\": 23,\n        \"BranchDescription\": \"TESORERIA\"\n      },\n      {\n        \"AmortizationTypeDescription\": \"AMORTIZABLE FRANCÉS (CONSTANTE TOTAL)\",\n        \"AmortizationTypeId\": 3,\n        \"Product\": {\n          \"ProductGUID\": \"cc2dc934-3de1-47c1-bf67-be92cc3ea16e\",\n          \"CurrencyDescription\": \"Pesos Uruguayos\",\n          \"KindDescription\": \"Billete\",\n          \"CurrencySign\": \"$\",\n          \"KindId\": 0,\n          \"ProductDescription\": \"ADELANTO SOBRE SUELDOS\",\n          \"CurrencyId\": 0\n        },\n        \"Term\": 365,\n        \"BranchId\": 1,\n        \"OriginalAmount\": 100000,\n        \"NumberOfInstallments\": 12,\n        \"InstallmentPeriodicity\": 30,\n        \"TotalPaidInstallments\": 0,\n        \"InstallmentValue\": 9985,\n        \"ExpirationDate\": \"2026-01-03\",\n        \"FirstUnpaidDate\": \"2025-02-03\",\n        \"StatusDescription\": \"Normal\",\n        \"AccountBalance\": -100000,\n        \"ValueDate\": \"2025-01-03\",\n        \"StatusId\": 0,\n        \"LoanGUID\": \"00000000-0000-0000-0000-000000000000\",\n        \"InterestRate\": 12.65,\n        \"BranchDescription\": \"Sucursal Beta\"\n      },\n      {\n        \"AmortizationTypeDescription\": \"AMORTIZABLE FRANCÉS (CONSTANTE TOTAL)\",\n        \"AmortizationTypeId\": 3,\n        \"Product\": {\n          \"ProductGUID\": \"cc2dc934-3de1-47c1-bf67-be92cc3ea16e\",\n          \"CurrencyDescription\": \"Pesos Uruguayos\",\n          \"KindDescription\": \"Billete\",\n          \"CurrencySign\": \"$\",\n          \"KindId\": 0,\n          \"ProductDescription\": \"ADELANTO SOBRE SUELDOS\",\n          \"CurrencyId\": 0\n        },\n        \"Term\": 365,\n        \"BranchId\": 1,\n        \"OriginalAmount\": 150000,\n        \"NumberOfInstallments\": 12,\n        \"InstallmentPeriodicity\": 30,\n        \"TotalPaidInstallments\": 0,\n        \"InstallmentValue\": 14597,\n        \"ExpirationDate\": \"2026-01-08\",\n        \"FirstUnpaidDate\": \"2025-02-08\",\n        \"StatusDescription\": \"Normal\",\n        \"AccountBalance\": -100000,\n        \"ValueDate\": \"2025-01-08\",\n        \"StatusId\": 0,\n        \"LoanGUID\": \"5f13d91d-9b48-4213-81ac-24a82adabcfe\",\n        \"InterestRate\": 12.65,\n        \"BranchDescription\": \"Sucursal Beta\"\n      },\n      {\n        \"AmortizationTypeDescription\": \"AMORTIZABLE FRANCÉS (CONSTANTE TOTAL)\",\n        \"AmortizationTypeId\": 3,\n        \"Product\": {\n          \"ProductGUID\": \"cc2dc934-3de1-47c1-bf67-be92cc3ea16e\",\n          \"CurrencyDescription\": \"Pesos Uruguayos\",\n          \"KindDescription\": \"Billete\",\n          \"CurrencySign\": \"$\",\n          \"KindId\": 0,\n          \"ProductDescription\": \"ADELANTO SOBRE SUELDOS\",\n          \"CurrencyId\": 0\n        },\n        \"Term\": 365,\n        \"BranchId\": 1,\n        \"OriginalAmount\": 100000,\n        \"NumberOfInstallments\": 12,\n        \"InstallmentPeriodicity\": 30,\n        \"TotalPaidInstallments\": 0,\n        \"InstallmentValue\": 9985,\n        \"ExpirationDate\": \"2026-01-08\",\n        \"FirstUnpaidDate\": \"2025-08-08\",\n        \"StatusDescription\": \"Normal\",\n        \"AccountBalance\": -100000,\n        \"ValueDate\": \"2025-01-08\",\n        \"StatusId\": 0,\n        \"LoanGUID\": \"12f8c706-d176-4192-8328-f55e24eebd7f\",\n        \"InterestRate\": 12.65,\n        \"BranchDescription\": \"Sucursal Beta\"\n      },\n      {\n        \"AmortizationTypeDescription\": \"AMORTIZABLE FRANCÉS (CONSTANTE TOTAL)\",\n        \"AmortizationTypeId\": 3,\n        \"Product\": {\n          \"ProductGUID\": \"cc2dc934-3de1-47c1-bf67-be92cc3ea16e\",\n          \"CurrencyDescription\": \"Pesos Uruguayos\",\n          \"KindDescription\": \"Billete\",\n          \"CurrencySign\": \"$\",\n          \"KindId\": 0,\n          \"ProductDescription\": \"ADELANTO SOBRE SUELDOS\",\n          \"CurrencyId\": 0\n        },\n        \"Term\": 365,\n        \"BranchId\": 1,\n        \"OriginalAmount\": 100000,\n        \"NumberOfInstallments\": 12,\n        \"InstallmentPeriodicity\": 30,\n        \"TotalPaidInstallments\": 0,\n        \"InstallmentValue\": 9985,\n        \"ExpirationDate\": \"2026-01-08\",\n        \"FirstUnpaidDate\": \"2025-02-08\",\n        \"StatusDescription\": \"Normal\",\n        \"AccountBalance\": -100000,\n        \"ValueDate\": \"2025-01-08\",\n        \"StatusId\": 0,\n        \"LoanGUID\": \"55c87436-4af6-49e2-a38d-b2c215dd86f5\",\n        \"InterestRate\": 12.65,\n        \"BranchDescription\": \"Sucursal Beta\"\n      },\n      {\n        \"AmortizationTypeDescription\": \"AMORTIZABLE FRANCÉS (CONSTANTE TOTAL)\",\n        \"AmortizationTypeId\": 3,\n        \"Product\": {\n          \"ProductGUID\": \"cc2dc934-3de1-47c1-bf67-be92cc3ea16e\",\n          \"CurrencyDescription\": \"Pesos Uruguayos\",\n          \"KindDescription\": \"Billete\",\n          \"CurrencySign\": \"$\",\n          \"KindId\": 0,\n          \"ProductDescription\": \"ADELANTO SOBRE SUELDOS\",\n          \"CurrencyId\": 0\n        },\n        \"Term\": 365,\n        \"BranchId\": 1,\n        \"OriginalAmount\": 100000,\n        \"NumberOfInstallments\": 12,\n        \"InstallmentPeriodicity\": 30,\n        \"TotalPaidInstallments\": 0,\n        \"InstallmentValue\": 9985,\n        \"ExpirationDate\": \"2026-01-08\",\n        \"FirstUnpaidDate\": \"2025-02-08\",\n        \"StatusDescription\": \"Normal\",\n        \"AccountBalance\": -100000,\n        \"ValueDate\": \"2025-01-08\",\n        \"StatusId\": 0,\n        \"LoanGUID\": \"67eeeb62-b0d0-4736-9d22-c32750cc26d5\",\n        \"InterestRate\": 12.65,\n        \"BranchDescription\": \"Sucursal Beta\"\n      },\n      {\n        \"AmortizationTypeDescription\": \"AMORTIZABLE FRANCÉS (CONSTANTE TOTAL)\",\n        \"AmortizationTypeId\": 3,\n        \"Product\": {\n          \"ProductGUID\": \"cc2dc934-3de1-47c1-bf67-be92cc3ea16e\",\n          \"CurrencyDescription\": \"Pesos Uruguayos\",\n          \"KindDescription\": \"Billete\",\n          \"CurrencySign\": \"$\",\n          \"KindId\": 0,\n          \"ProductDescription\": \"ADELANTO SOBRE SUELDOS\",\n          \"CurrencyId\": 0\n        },\n        \"Term\": 365,\n        \"BranchId\": 1,\n        \"OriginalAmount\": 100000,\n        \"NumberOfInstallments\": 12,\n        \"InstallmentPeriodicity\": 30,\n        \"TotalPaidInstallments\": 0,\n        \"InstallmentValue\": 9985,\n        \"ExpirationDate\": \"2026-01-08\",\n        \"FirstUnpaidDate\": \"2025-11-08\",\n        \"StatusDescription\": \"Normal\",\n        \"AccountBalance\": -100000,\n        \"ValueDate\": \"2025-01-08\",\n        \"StatusId\": 0,\n        \"LoanGUID\": \"58c6f0bc-4fec-432f-8761-fed37347f296\",\n        \"InterestRate\": 12.65,\n        \"BranchDescription\": \"Sucursal Beta\"\n      },\n      {\n        \"AmortizationTypeDescription\": \"AMORTIZABLE FRANCÉS (CONSTANTE TOTAL)\",\n        \"AmortizationTypeId\": 3,\n        \"Product\": {\n          \"ProductGUID\": \"cc2dc934-3de1-47c1-bf67-be92cc3ea16e\",\n          \"CurrencyDescription\": \"Pesos Uruguayos\",\n          \"KindDescription\": \"Billete\",\n          \"CurrencySign\": \"$\",\n          \"KindId\": 0,\n          \"ProductDescription\": \"ADELANTO SOBRE SUELDOS\",\n          \"CurrencyId\": 0\n        },\n        \"Term\": 273,\n        \"BranchId\": 1,\n        \"OriginalAmount\": 100000,\n        \"NumberOfInstallments\": 9,\n        \"InstallmentPeriodicity\": 30,\n        \"TotalPaidInstallments\": 0,\n        \"InstallmentValue\": 9985,\n        \"ExpirationDate\": \"2025-10-08\",\n        \"FirstUnpaidDate\": \"2025-04-08\",\n        \"StatusDescription\": \"Normal\",\n        \"AccountBalance\": -100000,\n        \"ValueDate\": \"2025-01-08\",\n        \"StatusId\": 0,\n        \"LoanGUID\": \"2a06e957-94e3-4138-8208-6739ee89c5a7\",\n        \"InterestRate\": 12.65,\n        \"BranchDescription\": \"Sucursal Beta\"\n      },\n      {\n        \"AmortizationTypeDescription\": \"AMORTIZABLE FRANCÉS (CONSTANTE TOTAL)\",\n        \"AmortizationTypeId\": 3,\n        \"Product\": {\n          \"ProductGUID\": \"cc2dc934-3de1-47c1-bf67-be92cc3ea16e\",\n          \"CurrencyDescription\": \"Pesos Uruguayos\",\n          \"KindDescription\": \"Billete\",\n          \"CurrencySign\": \"$\",\n          \"KindId\": 0,\n          \"ProductDescription\": \"ADELANTO SOBRE SUELDOS\",\n          \"CurrencyId\": 0\n        },\n        \"Term\": 365,\n        \"BranchId\": 1,\n        \"OriginalAmount\": 100000,\n        \"NumberOfInstallments\": 12,\n        \"InstallmentPeriodicity\": 30,\n        \"TotalPaidInstallments\": 0,\n        \"InstallmentValue\": 9985,\n        \"ExpirationDate\": \"2026-01-08\",\n        \"FirstUnpaidDate\": \"2025-02-08\",\n        \"StatusDescription\": \"Normal\",\n        \"AccountBalance\": -100000,\n        \"ValueDate\": \"2025-01-08\",\n        \"StatusId\": 0,\n        \"LoanGUID\": \"7d0636ce-a6d0-48f0-b772-bf2ee17f4fbc\",\n        \"InterestRate\": 12.65,\n        \"BranchDescription\": \"Sucursal Beta\"\n      },\n      {\n        \"AmortizationTypeDescription\": \"AMORTIZABLE FRANCÉS (CONSTANTE TOTAL)\",\n        \"AmortizationTypeId\": 3,\n        \"Product\": {\n          \"ProductGUID\": \"cc2dc934-3de1-47c1-bf67-be92cc3ea16e\",\n          \"CurrencyDescription\": \"Pesos Uruguayos\",\n          \"KindDescription\": \"Billete\",\n          \"CurrencySign\": \"$\",\n          \"KindId\": 0,\n          \"ProductDescription\": \"ADELANTO SOBRE SUELDOS\",\n          \"CurrencyId\": 0\n        },\n        \"Term\": 0,\n        \"BranchId\": 1,\n        \"OriginalAmount\": 151952,\n        \"NumberOfInstallments\": 0,\n        \"InstallmentPeriodicity\": 30,\n        \"TotalPaidInstallments\": 0,\n        \"InstallmentValue\": 15071,\n        \"StatusDescription\": \"Normal\",\n        \"AccountBalance\": -100000,\n        \"ValueDate\": \"2025-07-08\",\n        \"StatusId\": 0,\n        \"LoanGUID\": \"1766f6a9-c7e9-4ecf-8ae5-8202ad150377\",\n        \"InterestRate\": 20,\n        \"BranchDescription\": \"Sucursal Beta\"\n      },\n      {\n        \"AmortizationTypeDescription\": \"AMORTIZABLE FRANCÉS (CONSTANTE TOTAL)\",\n        \"AmortizationTypeId\": 3,\n        \"Product\": {\n          \"ProductGUID\": \"cc2dc934-3de1-47c1-bf67-be92cc3ea16e\",\n          \"CurrencyDescription\": \"Pesos Uruguayos\",\n          \"KindDescription\": \"Billete\",\n          \"CurrencySign\": \"$\",\n          \"KindId\": 0,\n          \"ProductDescription\": \"ADELANTO SOBRE SUELDOS\",\n          \"CurrencyId\": 0\n        },\n        \"Term\": 364,\n        \"BranchId\": 1,\n        \"OriginalAmount\": 122013,\n        \"NumberOfInstallments\": 12,\n        \"InstallmentPeriodicity\": 30,\n        \"TotalPaidInstallments\": 0,\n        \"InstallmentValue\": 12366,\n        \"ExpirationDate\": \"2026-07-12\",\n        \"StatusDescription\": \"Normal\",\n        \"AccountBalance\": -100000,\n        \"ValueDate\": \"2025-07-08\",\n        \"StatusId\": 0,\n        \"LoanGUID\": \"93faa6b6-360c-4204-89e4-318ce69d0533\",\n        \"InterestRate\": 20,\n        \"BranchDescription\": \"Sucursal Beta\"\n      },\n      {\n        \"AmortizationTypeDescription\": \"AMORTIZABLE FRANCÉS (CONSTANTE TOTAL)\",\n        \"AmortizationTypeId\": 3,\n        \"Product\": {\n          \"ProductGUID\": \"cc2dc934-3de1-47c1-bf67-be92cc3ea16e\",\n          \"CurrencyDescription\": \"Pesos Uruguayos\",\n          \"KindDescription\": \"Billete\",\n          \"CurrencySign\": \"$\",\n          \"KindId\": 0,\n          \"ProductDescription\": \"ADELANTO SOBRE SUELDOS\",\n          \"CurrencyId\": 0\n        },\n        \"Term\": 372,\n        \"BranchId\": 1,\n        \"OriginalAmount\": 135000,\n        \"NumberOfInstallments\": 12,\n        \"InstallmentPeriodicity\": 30,\n        \"TotalPaidInstallments\": 0,\n        \"InstallmentValue\": 14376,\n        \"ExpirationDate\": \"2026-02-12\",\n        \"StatusDescription\": \"Normal\",\n        \"AccountBalance\": -100000,\n        \"ValueDate\": \"2025-01-31\",\n        \"StatusId\": 0,\n        \"LoanGUID\": \"fdccf226-40f1-4fa2-8181-34fcb2849192\",\n        \"InterestRate\": 20,\n        \"BranchDescription\": \"Sucursal Beta\"\n      },\n      {\n        \"AmortizationTypeDescription\": \"AMORTIZABLE FRANCÉS (CONSTANTE TOTAL)\",\n        \"AmortizationTypeId\": 3,\n        \"Product\": {\n          \"ProductGUID\": \"cc2dc934-3de1-47c1-bf67-be92cc3ea16e\",\n          \"CurrencyDescription\": \"Pesos Uruguayos\",\n          \"KindDescription\": \"Billete\",\n          \"CurrencySign\": \"$\",\n          \"KindId\": 0,\n          \"ProductDescription\": \"ADELANTO SOBRE SUELDOS\",\n          \"CurrencyId\": 0\n        },\n        \"Term\": 372,\n        \"BranchId\": 1,\n        \"OriginalAmount\": 120000,\n        \"NumberOfInstallments\": 12,\n        \"InstallmentPeriodicity\": 30,\n        \"TotalPaidInstallments\": 0,\n        \"InstallmentValue\": 12915,\n        \"ExpirationDate\": \"2026-02-12\",\n        \"FirstUnpaidDate\": \"2025-03-12\",\n        \"StatusDescription\": \"Normal\",\n        \"AccountBalance\": -100000,\n        \"ValueDate\": \"2025-01-31\",\n        \"StatusId\": 0,\n        \"LoanGUID\": \"f0ff0277-fcf9-4f38-a89a-1d8c2003e131\",\n        \"InterestRate\": 20,\n        \"BranchDescription\": \"Sucursal Beta\"\n      },\n      {\n        \"AmortizationTypeDescription\": \"FLEXIBLE\",\n        \"AmortizationTypeId\": 6,\n        \"Product\": {\n          \"ProductGUID\": \"d4e7ea18-1292-48bf-b1af-13376ea7bb1c\",\n          \"CurrencyDescription\": \"Pesos Uruguayos\",\n          \"KindDescription\": \"Billete\",\n          \"CurrencySign\": \"$\",\n          \"KindId\": 0,\n          \"ProductDescription\": \"FLEXIBLE\",\n          \"CurrencyId\": 0\n        },\n        \"Term\": 360,\n        \"BranchId\": 1,\n        \"OriginalAmount\": 35000,\n        \"NumberOfInstallments\": 6,\n        \"InstallmentPeriodicity\": 30,\n        \"TotalPaidInstallments\": 0,\n        \"InstallmentValue\": 0,\n        \"ExpirationDate\": \"2026-04-30\",\n        \"FirstUnpaidDate\": \"2025-12-01\",\n        \"StatusDescription\": \"Normal\",\n        \"AccountBalance\": -100000,\n        \"ValueDate\": \"2025-11-01\",\n        \"StatusId\": 0,\n        \"LoanGUID\": \"2f7e42b0-1a78-4176-aa36-e16736e76db3\",\n        \"InterestRate\": 50,\n        \"BranchDescription\": \"Sucursal Beta\"\n      },\n      {\n        \"AmortizationTypeDescription\": \"FLEXIBLE\",\n        \"AmortizationTypeId\": 6,\n        \"Product\": {\n          \"ProductGUID\": \"d4e7ea18-1292-48bf-b1af-13376ea7bb1c\",\n          \"CurrencyDescription\": \"Pesos Uruguayos\",\n          \"KindDescription\": \"Billete\",\n          \"CurrencySign\": \"$\",\n          \"KindId\": 0,\n          \"ProductDescription\": \"FLEXIBLE\",\n          \"CurrencyId\": 0\n        },\n        \"Term\": 608,\n        \"BranchId\": 1,\n        \"OriginalAmount\": 15000,\n        \"NumberOfInstallments\": 10,\n        \"InstallmentPeriodicity\": 30,\n        \"TotalPaidInstallments\": 0,\n        \"InstallmentValue\": 0,\n        \"ExpirationDate\": \"2026-09-01\",\n        \"FirstUnpaidDate\": \"2025-12-01\",\n        \"StatusDescription\": \"Normal\",\n        \"AccountBalance\": -100000,\n        \"ValueDate\": \"2025-11-01\",\n        \"StatusId\": 0,\n        \"LoanGUID\": \"da0fcba1-fe81-41d9-bcbf-38bacb11d610\",\n        \"InterestRate\": 50,\n        \"BranchDescription\": \"Sucursal Beta\"\n      },\n      {\n        \"AmortizationTypeDescription\": \"AMORTIZABLE FRANCÉS (CONSTANTE TOTAL)\",\n        \"AmortizationTypeId\": 3,\n        \"Product\": {\n          \"ProductGUID\": \"cc2dc934-3de1-47c1-bf67-be92cc3ea16e\",\n          \"CurrencyDescription\": \"Pesos Uruguayos\",\n          \"KindDescription\": \"Billete\",\n          \"CurrencySign\": \"$\",\n          \"KindId\": 0,\n          \"ProductDescription\": \"ADELANTO SOBRE SUELDOS\",\n          \"CurrencyId\": 0\n        },\n        \"Term\": 360,\n        \"BranchId\": 1,\n        \"OriginalAmount\": 100000,\n        \"NumberOfInstallments\": 12,\n        \"InstallmentPeriodicity\": 30,\n        \"TotalPaidInstallments\": 0,\n        \"InstallmentValue\": 11924,\n        \"ExpirationDate\": \"2026-11-03\",\n        \"FirstUnpaidDate\": \"2025-12-03\",\n        \"StatusDescription\": \"Normal\",\n        \"AccountBalance\": -100000,\n        \"ValueDate\": \"2025-11-03\",\n        \"StatusId\": 0,\n        \"LoanGUID\": \"34c58bac-a09f-4708-9385-577d104d361c\",\n        \"InterestRate\": 65,\n        \"BranchDescription\": \"Sucursal Beta\"\n      },\n      {\n        \"AmortizationTypeDescription\": \"FLEXIBLE\",\n        \"AmortizationTypeId\": 6,\n        \"Product\": {\n          \"ProductGUID\": \"d4e7ea18-1292-48bf-b1af-13376ea7bb1c\",\n          \"CurrencyDescription\": \"Pesos Uruguayos\",\n          \"KindDescription\": \"Billete\",\n          \"CurrencySign\": \"$\",\n          \"KindId\": 0,\n          \"ProductDescription\": \"FLEXIBLE\",\n          \"CurrencyId\": 0\n        },\n        \"Term\": 300,\n        \"BranchId\": 1,\n        \"OriginalAmount\": 50000,\n        \"NumberOfInstallments\": 10,\n        \"InstallmentPeriodicity\": 30,\n        \"TotalPaidInstallments\": 0,\n        \"InstallmentValue\": 0,\n        \"ExpirationDate\": \"2027-12-26\",\n        \"FirstUnpaidDate\": \"2027-03-26\",\n        \"StatusDescription\": \"Normal\",\n        \"AccountBalance\": -100000,\n        \"ValueDate\": \"2027-02-26\",\n        \"StatusId\": 0,\n        \"LoanGUID\": \"282dc866-872c-428e-8f01-cdcc3c41b255\",\n        \"InterestRate\": 50,\n        \"BranchDescription\": \"Sucursal Beta\"\n      },\n      {\n        \"AmortizationTypeDescription\": \"AMORTIZABLE FRANCÉS (CONSTANTE TOTAL)\",\n        \"AmortizationTypeId\": 3,\n        \"Product\": {\n          \"ProductGUID\": \"cc2dc934-3de1-47c1-bf67-be92cc3ea16e\",\n          \"CurrencyDescription\": \"Pesos Uruguayos\",\n          \"KindDescription\": \"Billete\",\n          \"CurrencySign\": \"$\",\n          \"KindId\": 0,\n          \"ProductDescription\": \"ADELANTO SOBRE SUELDOS\",\n          \"CurrencyId\": 0\n        },\n        \"Term\": 630,\n        \"BranchId\": 1,\n        \"OriginalAmount\": 100000,\n        \"NumberOfInstallments\": 21,\n        \"InstallmentPeriodicity\": 30,\n        \"TotalPaidInstallments\": 0,\n        \"InstallmentValue\": 8308,\n        \"ExpirationDate\": \"2028-12-31\",\n        \"FirstUnpaidDate\": \"2027-08-01\",\n        \"StatusDescription\": \"Normal\",\n        \"AccountBalance\": -100000,\n        \"ValueDate\": \"2027-03-31\",\n        \"StatusId\": 0,\n        \"LoanGUID\": \"18ad145f-c779-4213-a92d-60b45e9ceabe\",\n        \"InterestRate\": 60,\n        \"BranchDescription\": \"Sucursal Beta\"\n      },\n      {\n        \"AmortizationTypeDescription\": \"AMORTIZABLE FRANCÉS (CONSTANTE TOTAL)\",\n        \"AmortizationTypeId\": 3,\n        \"Product\": {\n          \"ProductGUID\": \"204db26d-f2f0-453e-b167-2b8496fc6cca\",\n          \"CurrencyDescription\": \"Pesos Uruguayos\",\n          \"KindDescription\": \"Billete\",\n          \"CurrencySign\": \"$\",\n          \"KindId\": 0,\n          \"ProductDescription\": \"PRÉSTAMO PERSONAL\",\n          \"CurrencyId\": 0\n        },\n        \"Term\": 214,\n        \"BranchId\": 1,\n        \"OriginalAmount\": 1000,\n        \"NumberOfInstallments\": 7,\n        \"InstallmentPeriodicity\": 30,\n        \"TotalPaidInstallments\": 0,\n        \"InstallmentValue\": 1393,\n        \"ExpirationDate\": \"2028-01-12\",\n        \"FirstUnpaidDate\": \"2027-07-12\",\n        \"StatusDescription\": \"Normal\",\n        \"AccountBalance\": -100000,\n        \"ValueDate\": \"2027-06-12\",\n        \"StatusId\": 0,\n        \"LoanGUID\": \"6dac0e4a-d922-4c66-be3d-b75a7e72aa67\",\n        \"InterestRate\": 20,\n        \"BranchDescription\": \"Sucursal Beta\"\n      },\n      {\n        \"AmortizationTypeDescription\": \"AMORTIZABLE FRANCÉS (CONSTANTE TOTAL)\",\n        \"AmortizationTypeId\": 3,\n        \"Product\": {\n          \"ProductGUID\": \"2513af07-a65c-4454-b907-855940e08727\",\n          \"CurrencyDescription\": \"DÓLAR ESTADOUNIDENSE - BILLETE\",\n          \"KindDescription\": \"Billete\",\n          \"CurrencySign\": \"U$D\",\n          \"KindId\": 0,\n          \"ProductDescription\": \"PRÉSTAMO PERSONAL\",\n          \"CurrencyId\": 2225\n        },\n        \"Term\": 394,\n        \"BranchId\": 1,\n        \"OriginalAmount\": 1000,\n        \"NumberOfInstallments\": 12,\n        \"InstallmentPeriodicity\": 30,\n        \"TotalPaidInstallments\": 0,\n        \"InstallmentValue\": 208,\n        \"ExpirationDate\": \"2028-07-12\",\n        \"FirstUnpaidDate\": \"2027-08-12\",\n        \"StatusDescription\": \"Normal\",\n        \"AccountBalance\": -100000,\n        \"ValueDate\": \"2027-06-14\",\n        \"StatusId\": 0,\n        \"LoanGUID\": \"86c79e9c-4d46-4125-8c41-87c5d6384828\",\n        \"InterestRate\": 20,\n        \"BranchDescription\": \"Sucursal Beta\"\n      },\n      {\n        \"AmortizationTypeDescription\": \"AMORTIZABLE FRANCÉS (CONSTANTE TOTAL)\",\n        \"AmortizationTypeId\": 3,\n        \"Product\": {\n          \"ProductGUID\": \"cc2dc934-3de1-47c1-bf67-be92cc3ea16e\",\n          \"CurrencyDescription\": \"Pesos Uruguayos\",\n          \"KindDescription\": \"Billete\",\n          \"CurrencySign\": \"$\",\n          \"KindId\": 0,\n          \"ProductDescription\": \"ADELANTO SOBRE SUELDOS\",\n          \"CurrencyId\": 0\n        },\n        \"Term\": 360,\n        \"BranchId\": 90,\n        \"OriginalAmount\": 101680,\n        \"NumberOfInstallments\": 12,\n        \"InstallmentPeriodicity\": 30,\n        \"TotalPaidInstallments\": 0,\n        \"InstallmentValue\": 11587,\n        \"ExpirationDate\": \"2028-07-15\",\n        \"FirstUnpaidDate\": \"2027-09-15\",\n        \"StatusDescription\": \"Normal\",\n        \"AccountBalance\": -100000,\n        \"StatusId\": 0,\n        \"LoanGUID\": \"a10f0422-09ce-4015-a95b-cb4a8a98b6d8\",\n        \"InterestRate\": 57.5,\n        \"BranchDescription\": \"TESORERIA\"\n      },\n      {\n        \"AmortizationTypeDescription\": \"AMORTIZABLE FRANCÉS (CONSTANTE TOTAL)\",\n        \"AmortizationTypeId\": 3,\n        \"Product\": {\n          \"ProductGUID\": \"f78f8edd-f2dd-473c-a20f-bc6416ec85e7\",\n          \"CurrencyDescription\": \"Pesos Uruguayos\",\n          \"KindDescription\": \"Billete\",\n          \"CurrencySign\": \"$\",\n          \"KindId\": 0,\n          \"ProductDescription\": \"PRUEBA FACUNDO\",\n          \"CurrencyId\": 0\n        },\n        \"Term\": 364,\n        \"BranchId\": 1000,\n        \"OriginalAmount\": 1000,\n        \"NumberOfInstallments\": 12,\n        \"InstallmentPeriodicity\": 30,\n        \"TotalPaidInstallments\": 0,\n        \"InstallmentValue\": 303,\n        \"ExpirationDate\": \"2026-01-12\",\n        \"FirstUnpaidDate\": \"2025-02-12\",\n        \"StatusDescription\": \"Normal\",\n        \"AccountBalance\": -100000,\n        \"ValueDate\": \"2025-01-08\",\n        \"StatusId\": 0,\n        \"LoanGUID\": \"51b4f3d7-2976-4e1a-bb03-545ad05e219e\",\n        \"InterestRate\": 20,\n        \"BranchDescription\": \"Sucursa demo\"\n      },\n      {\n        \"AmortizationTypeDescription\": \"AMORTIZABLE FRANCÉS (CONSTANTE TOTAL)\",\n        \"AmortizationTypeId\": 3,\n        \"Product\": {\n          \"ProductGUID\": \"f78f8edd-f2dd-473c-a20f-bc6416ec85e7\",\n          \"CurrencyDescription\": \"Pesos Uruguayos\",\n          \"KindDescription\": \"Billete\",\n          \"CurrencySign\": \"$\",\n          \"KindId\": 0,\n          \"ProductDescription\": \"PRUEBA FACUNDO\",\n          \"CurrencyId\": 0\n        },\n        \"Term\": 364,\n        \"BranchId\": 1000,\n        \"OriginalAmount\": 1000,\n        \"NumberOfInstallments\": 12,\n        \"InstallmentPeriodicity\": 30,\n        \"TotalPaidInstallments\": 0,\n        \"InstallmentValue\": 303,\n        \"ExpirationDate\": \"2026-01-12\",\n        \"FirstUnpaidDate\": \"2025-03-12\",\n        \"StatusDescription\": \"Normal\",\n        \"AccountBalance\": -100000,\n        \"ValueDate\": \"2025-01-08\",\n        \"StatusId\": 0,\n        \"LoanGUID\": \"de747bbb-8596-4b84-9cd4-7e4663a22a24\",\n        \"InterestRate\": 20,\n        \"BranchDescription\": \"Sucursa demo\"\n      },\n      {\n        \"AmortizationTypeDescription\": \"AMORTIZABLE FRANCÉS (CONSTANTE TOTAL)\",\n        \"AmortizationTypeId\": 3,\n        \"Product\": {\n          \"ProductGUID\": \"bf0d7e10-dce6-4bd4-b866-9984556613ec\",\n          \"CurrencyDescription\": \"Pesos Uruguayos\",\n          \"KindDescription\": \"Billete\",\n          \"CurrencySign\": \"$\",\n          \"KindId\": 0,\n          \"ProductDescription\": \"GRUPALES\",\n          \"CurrencyId\": 0\n        },\n        \"Term\": 110,\n        \"BranchId\": 1,\n        \"OriginalAmount\": 12600,\n        \"NumberOfInstallments\": 16,\n        \"InstallmentPeriodicity\": 7,\n        \"TotalPaidInstallments\": 0,\n        \"InstallmentValue\": 1309,\n        \"ExpirationDate\": \"2027-10-30\",\n        \"FirstUnpaidDate\": \"2027-07-17\",\n        \"StatusDescription\": \"Normal\",\n        \"AccountBalance\": -100000,\n        \"ValueDate\": \"2027-07-10\",\n        \"StatusId\": 0,\n        \"LoanGUID\": \"d1320758-1d85-4a3d-ae62-30d44165691d\",\n        \"InterestRate\": 18.5,\n        \"BranchDescription\": \"Sucursal Beta\"\n      },\n      {\n        \"AmortizationTypeDescription\": \"AMORTIZABLE FRANCÉS (CONSTANTE TOTAL)\",\n        \"AmortizationTypeId\": 3,\n        \"Product\": {\n          \"ProductGUID\": \"bf0d7e10-dce6-4bd4-b866-9984556613ec\",\n          \"CurrencyDescription\": \"Pesos Uruguayos\",\n          \"KindDescription\": \"Billete\",\n          \"CurrencySign\": \"$\",\n          \"KindId\": 0,\n          \"ProductDescription\": \"GRUPALES\",\n          \"CurrencyId\": 0\n        },\n        \"Term\": 111,\n        \"BranchId\": 1,\n        \"OriginalAmount\": 10000,\n        \"NumberOfInstallments\": 16,\n        \"InstallmentPeriodicity\": 7,\n        \"TotalPaidInstallments\": 0,\n        \"InstallmentValue\": 659,\n        \"ExpirationDate\": \"2028-03-22\",\n        \"FirstUnpaidDate\": \"2027-12-08\",\n        \"StatusDescription\": \"Normal\",\n        \"AccountBalance\": -100000,\n        \"ValueDate\": \"2027-12-01\",\n        \"StatusId\": 0,\n        \"LoanGUID\": \"ba5c739b-2a47-4010-b72f-c995985e6da7\",\n        \"InterestRate\": 7,\n        \"BranchDescription\": \"Sucursal Beta\"\n      },\n      {\n        \"AmortizationTypeDescription\": \"AMORTIZABLE FRANCÉS (CONSTANTE TOTAL)\",\n        \"AmortizationTypeId\": 3,\n        \"Product\": {\n          \"ProductGUID\": \"bf0d7e10-dce6-4bd4-b866-9984556613ec\",\n          \"CurrencyDescription\": \"Pesos Uruguayos\",\n          \"KindDescription\": \"Billete\",\n          \"CurrencySign\": \"$\",\n          \"KindId\": 0,\n          \"ProductDescription\": \"GRUPALES\",\n          \"CurrencyId\": 0\n        },\n        \"Term\": 83,\n        \"BranchId\": 91,\n        \"OriginalAmount\": 30000,\n        \"NumberOfInstallments\": 12,\n        \"InstallmentPeriodicity\": 7,\n        \"TotalPaidInstallments\": 0,\n        \"InstallmentValue\": 3127,\n        \"ExpirationDate\": \"2027-07-06\",\n        \"FirstUnpaidDate\": \"2027-04-20\",\n        \"StatusDescription\": \"Normal\",\n        \"AccountBalance\": -100000,\n        \"ValueDate\": \"2027-04-13\",\n        \"StatusId\": 0,\n        \"LoanGUID\": \"765fb997-7172-4931-b7be-3623f6bc5e58\",\n        \"InterestRate\": 15,\n        \"BranchDescription\": \"TESORERIA BONOS\"\n      }\n    ],\n    \"AccountBalance\": \"\",\n    \"AmortizationTypeId\": 0,\n    \"AmortizationTypeDescription\": \"\",\n    \"BranchId\": 0,\n    \"BranchDescription\": \"\",\n    \"DateOfLastTotalPayment\": \"\",\n    \"ExpirationDate\": \"\",\n    \"FirstUnpaidDate\": \"\",\n    \"InstallmentPeriodicity\": 0,\n    \"InstallmentValue\": 0,\n    \"InterestRate\": 0,\n    \"LoanGUID\": \"\",\n    \"NumberOfInstallments\": 0,\n    \"OriginalAmount\": 0,\n    \"Product\": {\n      \"CurrencyId\": \"\",\n      \"CurrencyDescription\": \"\",\n      \"CurrencySign\": \"\",\n      \"KindId\": 0,\n      \"KindDescription\": \"\",\n      \"ProductDescription\": \"\",\n      \"ProductGUId\": \"\"\n    },\n    \"StatusId\": 0,\n    \"StatusDescription\": \"\",\n    \"Term\": 0,\n    \"TotalPaidInstallments\": 0,\n    \"ValueDate\": \"\"\n  },\n  \"BusinessErrors\": \"\",\n  \"Btoutreq\": {\n    \"Estado\": \"OK\",\n    \"Fecha\": \"2026-01-01\",\n    \"Hora\": \"00:00:00\",\n    \"Numero\": \"00000000\",\n    \"Servicio\": \"PublicLoans.getCustomerLoans\",\n    \"Requerimiento\": \"1\",\n    \"Canal\": \"BTDIGITAL\"\n  }\n}",
      "xml": "",
      "tabs": [
        {
          "name": "JSON",
          "lang": "json",
          "code": "{\n  \"Btinreq\": {\n    \"Canal\": \"BTDIGITAL\",\n    \"Usuario\": \"INSTALADOR\",\n    \"Device\": \"INSTALADOR\",\n    \"Requerimiento\": \"1\",\n    \"Token\": \"TOKEN_AQUI\"\n  },\n  \"customerLoans\": {\n    \"customerLoan\": [\n      {\n        \"AmortizationTypeDescription\": \"AMORTIZABLE FRANCÉS (CONSTANTE TOTAL)\",\n        \"AmortizationTypeId\": 3,\n        \"Product\": {\n          \"ProductGUID\": \"d6328022-6f93-4afc-b59b-a29f435aba41\",\n          \"CurrencyDescription\": \"Pesos Uruguayos\",\n          \"KindDescription\": \"Billete\",\n          \"CurrencySign\": \"$\",\n          \"KindId\": 0,\n          \"ProductDescription\": \"COMPRA DE VIVIENDA\",\n          \"CurrencyId\": 0\n        },\n        \"Term\": 699,\n        \"BranchId\": 1,\n        \"OriginalAmount\": 100000,\n        \"NumberOfInstallments\": 24,\n        \"InstallmentPeriodicity\": 30,\n        \"TotalPaidInstallments\": 0,\n        \"InstallmentValue\": 5544.14,\n        \"ExpirationDate\": \"2026-12-08\",\n        \"FirstUnpaidDate\": \"2025-01-08\",\n        \"StatusDescription\": \"Normal\",\n        \"AccountBalance\": -100000,\n        \"ValueDate\": \"2025-01-08\",\n        \"StatusId\": 0,\n        \"LoanGUID\": \"d59d0a0b-ff0e-4264-a425-c8dc87027c0a\",\n        \"InterestRate\": 23,\n        \"BranchDescription\": \"Sucursal Beta\"\n      },\n      {\n        \"AmortizationTypeDescription\": \"AMORTIZABLE FRANCÉS (CONSTANTE TOTAL)\",\n        \"AmortizationTypeId\": 3,\n        \"Product\": {\n          \"ProductGUID\": \"d6328022-6f93-4afc-b59b-a29f435aba41\",\n          \"CurrencyDescription\": \"Pesos Uruguayos\",\n          \"KindDescription\": \"Billete\",\n          \"CurrencySign\": \"$\",\n          \"KindId\": 0,\n          \"ProductDescription\": \"COMPRA DE VIVIENDA\",\n          \"CurrencyId\": 0\n        },\n        \"Term\": 1795,\n        \"BranchId\": 1,\n        \"OriginalAmount\": 100000,\n        \"NumberOfInstallments\": 60,\n        \"InstallmentPeriodicity\": 30,\n        \"TotalPaidInstallments\": 0,\n        \"InstallmentValue\": 3203.86,\n        \"ExpirationDate\": \"2030-07-08\",\n        \"FirstUnpaidDate\": \"2027-05-10\",\n        \"StatusDescription\": \"Normal\",\n        \"AccountBalance\": -100000,\n        \"ValueDate\": \"2025-08-08\",\n        \"StatusId\": 0,\n        \"LoanGUID\": \"ceec5783-b363-4263-afe6-62387c8f72d8\",\n        \"InterestRate\": 23,\n        \"BranchDescription\": \"Sucursal Beta\"\n      },\n      {\n        \"AmortizationTypeDescription\": \"AMORTIZABLE FRANCÉS (CONSTANTE TOTAL)\",\n        \"AmortizationTypeId\": 3,\n        \"Product\": {\n          \"ProductGUID\": \"d6328022-6f93-4afc-b59b-a29f435aba41\",\n          \"CurrencyDescription\": \"Pesos Uruguayos\",\n          \"KindDescription\": \"Billete\",\n          \"CurrencySign\": \"$\",\n          \"KindId\": 0,\n          \"ProductDescription\": \"COMPRA DE VIVIENDA\",\n          \"CurrencyId\": 0\n        },\n        \"Term\": 347,\n        \"BranchId\": 1,\n        \"OriginalAmount\": 100000,\n        \"NumberOfInstallments\": 12,\n        \"InstallmentPeriodicity\": 30,\n        \"TotalPaidInstallments\": 0,\n        \"InstallmentValue\": 9703.77,\n        \"ExpirationDate\": \"2028-02-08\",\n        \"FirstUnpaidDate\": \"2027-04-08\",\n        \"StatusDescription\": \"Normal\",\n        \"AccountBalance\": -100000,\n        \"ValueDate\": \"2027-02-26\",\n        \"StatusId\": 0,\n        \"LoanGUID\": \"973d2029-da60-45f2-9edc-7feede4e4933\",\n        \"InterestRate\": 23,\n        \"BranchDescription\": \"Sucursal Beta\"\n      },\n      {\n        \"AmortizationTypeDescription\": \"AMORTIZABLE FRANCÉS (CONSTANTE TOTAL)\",\n        \"AmortizationTypeId\": 3,\n        \"Product\": {\n          \"ProductGUID\": \"b28af066-a6af-4ad5-9ad6-bfc925f93eee\",\n          \"CurrencyDescription\": \"Pesos Uruguayos\",\n          \"KindDescription\": \"Billete\",\n          \"CurrencySign\": \"$\",\n          \"KindId\": 0,\n          \"ProductDescription\": \"REFACCIÓN DE VIVIENDA\",\n          \"CurrencyId\": 0\n        },\n        \"Term\": 360,\n        \"BranchId\": 90,\n        \"OriginalAmount\": 100000,\n        \"NumberOfInstallments\": 12,\n        \"InstallmentPeriodicity\": 30,\n        \"TotalPaidInstallments\": 0,\n        \"InstallmentValue\": 11117.26,\n        \"ExpirationDate\": \"2028-06-08\",\n        \"FirstUnpaidDate\": \"2027-07-08\",\n        \"StatusDescription\": \"Normal\",\n        \"AccountBalance\": -100000,\n        \"ValueDate\": \"2027-06-14\",\n        \"StatusId\": 0,\n        \"LoanGUID\": \"83cc0e94-5115-482b-aeb9-0934a38e5905\",\n        \"InterestRate\": 23,\n        \"BranchDescription\": \"TESORERIA\"\n      },\n      {\n        \"AmortizationTypeDescription\": \"AMORTIZABLE FRANCÉS (CONSTANTE TOTAL)\",\n        \"AmortizationTypeId\": 3,\n        \"Product\": {\n          \"ProductGUID\": \"b28af066-a6af-4ad5-9ad6-bfc925f93eee\",\n          \"CurrencyDescription\": \"Pesos Uruguayos\",\n          \"KindDescription\": \"Billete\",\n          \"CurrencySign\": \"$\",\n          \"KindId\": 0,\n          \"ProductDescription\": \"REFACCIÓN DE VIVIENDA\",\n          \"CurrencyId\": 0\n        },\n        \"Term\": 360,\n        \"BranchId\": 90,\n        \"OriginalAmount\": 100000,\n        \"NumberOfInstallments\": 12,\n        \"InstallmentPeriodicity\": 30,\n        \"TotalPaidInstallments\": 0,\n        \"InstallmentValue\": 11117.26,\n        \"ExpirationDate\": \"2028-06-08\",\n        \"FirstUnpaidDate\": \"2027-07-08\",\n        \"StatusDescription\": \"Normal\",\n        \"AccountBalance\": -100000,\n        \"ValueDate\": \"2027-06-14\",\n        \"StatusId\": 0,\n        \"LoanGUID\": \"bdde1d9a-bdd5-4490-a3e4-02de8d7f35e7\",\n        \"InterestRate\": 23,\n        \"BranchDescription\": \"TESORERIA\"\n      },\n      {\n        \"AmortizationTypeDescription\": \"AMORTIZABLE FRANCÉS (CONSTANTE TOTAL)\",\n        \"AmortizationTypeId\": 3,\n        \"Product\": {\n          \"ProductGUID\": \"cc2dc934-3de1-47c1-bf67-be92cc3ea16e\",\n          \"CurrencyDescription\": \"Pesos Uruguayos\",\n          \"KindDescription\": \"Billete\",\n          \"CurrencySign\": \"$\",\n          \"KindId\": 0,\n          \"ProductDescription\": \"ADELANTO SOBRE SUELDOS\",\n          \"CurrencyId\": 0\n        },\n        \"Term\": 365,\n        \"BranchId\": 1,\n        \"OriginalAmount\": 100000,\n        \"NumberOfInstallments\": 12,\n        \"InstallmentPeriodicity\": 30,\n        \"TotalPaidInstallments\": 0,\n        \"InstallmentValue\": 9985,\n        \"ExpirationDate\": \"2026-01-03\",\n        \"FirstUnpaidDate\": \"2025-02-03\",\n        \"StatusDescription\": \"Normal\",\n        \"AccountBalance\": -100000,\n        \"ValueDate\": \"2025-01-03\",\n        \"StatusId\": 0,\n        \"LoanGUID\": \"00000000-0000-0000-0000-000000000000\",\n        \"InterestRate\": 12.65,\n        \"BranchDescription\": \"Sucursal Beta\"\n      },\n      {\n        \"AmortizationTypeDescription\": \"AMORTIZABLE FRANCÉS (CONSTANTE TOTAL)\",\n        \"AmortizationTypeId\": 3,\n        \"Product\": {\n          \"ProductGUID\": \"cc2dc934-3de1-47c1-bf67-be92cc3ea16e\",\n          \"CurrencyDescription\": \"Pesos Uruguayos\",\n          \"KindDescription\": \"Billete\",\n          \"CurrencySign\": \"$\",\n          \"KindId\": 0,\n          \"ProductDescription\": \"ADELANTO SOBRE SUELDOS\",\n          \"CurrencyId\": 0\n        },\n        \"Term\": 365,\n        \"BranchId\": 1,\n        \"OriginalAmount\": 150000,\n        \"NumberOfInstallments\": 12,\n        \"InstallmentPeriodicity\": 30,\n        \"TotalPaidInstallments\": 0,\n        \"InstallmentValue\": 14597,\n        \"ExpirationDate\": \"2026-01-08\",\n        \"FirstUnpaidDate\": \"2025-02-08\",\n        \"StatusDescription\": \"Normal\",\n        \"AccountBalance\": -100000,\n        \"ValueDate\": \"2025-01-08\",\n        \"StatusId\": 0,\n        \"LoanGUID\": \"5f13d91d-9b48-4213-81ac-24a82adabcfe\",\n        \"InterestRate\": 12.65,\n        \"BranchDescription\": \"Sucursal Beta\"\n      },\n      {\n        \"AmortizationTypeDescription\": \"AMORTIZABLE FRANCÉS (CONSTANTE TOTAL)\",\n        \"AmortizationTypeId\": 3,\n        \"Product\": {\n          \"ProductGUID\": \"cc2dc934-3de1-47c1-bf67-be92cc3ea16e\",\n          \"CurrencyDescription\": \"Pesos Uruguayos\",\n          \"KindDescription\": \"Billete\",\n          \"CurrencySign\": \"$\",\n          \"KindId\": 0,\n          \"ProductDescription\": \"ADELANTO SOBRE SUELDOS\",\n          \"CurrencyId\": 0\n        },\n        \"Term\": 365,\n        \"BranchId\": 1,\n        \"OriginalAmount\": 100000,\n        \"NumberOfInstallments\": 12,\n        \"InstallmentPeriodicity\": 30,\n        \"TotalPaidInstallments\": 0,\n        \"InstallmentValue\": 9985,\n        \"ExpirationDate\": \"2026-01-08\",\n        \"FirstUnpaidDate\": \"2025-08-08\",\n        \"StatusDescription\": \"Normal\",\n        \"AccountBalance\": -100000,\n        \"ValueDate\": \"2025-01-08\",\n        \"StatusId\": 0,\n        \"LoanGUID\": \"12f8c706-d176-4192-8328-f55e24eebd7f\",\n        \"InterestRate\": 12.65,\n        \"BranchDescription\": \"Sucursal Beta\"\n      },\n      {\n        \"AmortizationTypeDescription\": \"AMORTIZABLE FRANCÉS (CONSTANTE TOTAL)\",\n        \"AmortizationTypeId\": 3,\n        \"Product\": {\n          \"ProductGUID\": \"cc2dc934-3de1-47c1-bf67-be92cc3ea16e\",\n          \"CurrencyDescription\": \"Pesos Uruguayos\",\n          \"KindDescription\": \"Billete\",\n          \"CurrencySign\": \"$\",\n          \"KindId\": 0,\n          \"ProductDescription\": \"ADELANTO SOBRE SUELDOS\",\n          \"CurrencyId\": 0\n        },\n        \"Term\": 365,\n        \"BranchId\": 1,\n        \"OriginalAmount\": 100000,\n        \"NumberOfInstallments\": 12,\n        \"InstallmentPeriodicity\": 30,\n        \"TotalPaidInstallments\": 0,\n        \"InstallmentValue\": 9985,\n        \"ExpirationDate\": \"2026-01-08\",\n        \"FirstUnpaidDate\": \"2025-02-08\",\n        \"StatusDescription\": \"Normal\",\n        \"AccountBalance\": -100000,\n        \"ValueDate\": \"2025-01-08\",\n        \"StatusId\": 0,\n        \"LoanGUID\": \"55c87436-4af6-49e2-a38d-b2c215dd86f5\",\n        \"InterestRate\": 12.65,\n        \"BranchDescription\": \"Sucursal Beta\"\n      },\n      {\n        \"AmortizationTypeDescription\": \"AMORTIZABLE FRANCÉS (CONSTANTE TOTAL)\",\n        \"AmortizationTypeId\": 3,\n        \"Product\": {\n          \"ProductGUID\": \"cc2dc934-3de1-47c1-bf67-be92cc3ea16e\",\n          \"CurrencyDescription\": \"Pesos Uruguayos\",\n          \"KindDescription\": \"Billete\",\n          \"CurrencySign\": \"$\",\n          \"KindId\": 0,\n          \"ProductDescription\": \"ADELANTO SOBRE SUELDOS\",\n          \"CurrencyId\": 0\n        },\n        \"Term\": 365,\n        \"BranchId\": 1,\n        \"OriginalAmount\": 100000,\n        \"NumberOfInstallments\": 12,\n        \"InstallmentPeriodicity\": 30,\n        \"TotalPaidInstallments\": 0,\n        \"InstallmentValue\": 9985,\n        \"ExpirationDate\": \"2026-01-08\",\n        \"FirstUnpaidDate\": \"2025-02-08\",\n        \"StatusDescription\": \"Normal\",\n        \"AccountBalance\": -100000,\n        \"ValueDate\": \"2025-01-08\",\n        \"StatusId\": 0,\n        \"LoanGUID\": \"67eeeb62-b0d0-4736-9d22-c32750cc26d5\",\n        \"InterestRate\": 12.65,\n        \"BranchDescription\": \"Sucursal Beta\"\n      },\n      {\n        \"AmortizationTypeDescription\": \"AMORTIZABLE FRANCÉS (CONSTANTE TOTAL)\",\n        \"AmortizationTypeId\": 3,\n        \"Product\": {\n          \"ProductGUID\": \"cc2dc934-3de1-47c1-bf67-be92cc3ea16e\",\n          \"CurrencyDescription\": \"Pesos Uruguayos\",\n          \"KindDescription\": \"Billete\",\n          \"CurrencySign\": \"$\",\n          \"KindId\": 0,\n          \"ProductDescription\": \"ADELANTO SOBRE SUELDOS\",\n          \"CurrencyId\": 0\n        },\n        \"Term\": 365,\n        \"BranchId\": 1,\n        \"OriginalAmount\": 100000,\n        \"NumberOfInstallments\": 12,\n        \"InstallmentPeriodicity\": 30,\n        \"TotalPaidInstallments\": 0,\n        \"InstallmentValue\": 9985,\n        \"ExpirationDate\": \"2026-01-08\",\n        \"FirstUnpaidDate\": \"2025-11-08\",\n        \"StatusDescription\": \"Normal\",\n        \"AccountBalance\": -100000,\n        \"ValueDate\": \"2025-01-08\",\n        \"StatusId\": 0,\n        \"LoanGUID\": \"58c6f0bc-4fec-432f-8761-fed37347f296\",\n        \"InterestRate\": 12.65,\n        \"BranchDescription\": \"Sucursal Beta\"\n      },\n      {\n        \"AmortizationTypeDescription\": \"AMORTIZABLE FRANCÉS (CONSTANTE TOTAL)\",\n        \"AmortizationTypeId\": 3,\n        \"Product\": {\n          \"ProductGUID\": \"cc2dc934-3de1-47c1-bf67-be92cc3ea16e\",\n          \"CurrencyDescription\": \"Pesos Uruguayos\",\n          \"KindDescription\": \"Billete\",\n          \"CurrencySign\": \"$\",\n          \"KindId\": 0,\n          \"ProductDescription\": \"ADELANTO SOBRE SUELDOS\",\n          \"CurrencyId\": 0\n        },\n        \"Term\": 273,\n        \"BranchId\": 1,\n        \"OriginalAmount\": 100000,\n        \"NumberOfInstallments\": 9,\n        \"InstallmentPeriodicity\": 30,\n        \"TotalPaidInstallments\": 0,\n        \"InstallmentValue\": 9985,\n        \"ExpirationDate\": \"2025-10-08\",\n        \"FirstUnpaidDate\": \"2025-04-08\",\n        \"StatusDescription\": \"Normal\",\n        \"AccountBalance\": -100000,\n        \"ValueDate\": \"2025-01-08\",\n        \"StatusId\": 0,\n        \"LoanGUID\": \"2a06e957-94e3-4138-8208-6739ee89c5a7\",\n        \"InterestRate\": 12.65,\n        \"BranchDescription\": \"Sucursal Beta\"\n      },\n      {\n        \"AmortizationTypeDescription\": \"AMORTIZABLE FRANCÉS (CONSTANTE TOTAL)\",\n        \"AmortizationTypeId\": 3,\n        \"Product\": {\n          \"ProductGUID\": \"cc2dc934-3de1-47c1-bf67-be92cc3ea16e\",\n          \"CurrencyDescription\": \"Pesos Uruguayos\",\n          \"KindDescription\": \"Billete\",\n          \"CurrencySign\": \"$\",\n          \"KindId\": 0,\n          \"ProductDescription\": \"ADELANTO SOBRE SUELDOS\",\n          \"CurrencyId\": 0\n        },\n        \"Term\": 365,\n        \"BranchId\": 1,\n        \"OriginalAmount\": 100000,\n        \"NumberOfInstallments\": 12,\n        \"InstallmentPeriodicity\": 30,\n        \"TotalPaidInstallments\": 0,\n        \"InstallmentValue\": 9985,\n        \"ExpirationDate\": \"2026-01-08\",\n        \"FirstUnpaidDate\": \"2025-02-08\",\n        \"StatusDescription\": \"Normal\",\n        \"AccountBalance\": -100000,\n        \"ValueDate\": \"2025-01-08\",\n        \"StatusId\": 0,\n        \"LoanGUID\": \"7d0636ce-a6d0-48f0-b772-bf2ee17f4fbc\",\n        \"InterestRate\": 12.65,\n        \"BranchDescription\": \"Sucursal Beta\"\n      },\n      {\n        \"AmortizationTypeDescription\": \"AMORTIZABLE FRANCÉS (CONSTANTE TOTAL)\",\n        \"AmortizationTypeId\": 3,\n        \"Product\": {\n          \"ProductGUID\": \"cc2dc934-3de1-47c1-bf67-be92cc3ea16e\",\n          \"CurrencyDescription\": \"Pesos Uruguayos\",\n          \"KindDescription\": \"Billete\",\n          \"CurrencySign\": \"$\",\n          \"KindId\": 0,\n          \"ProductDescription\": \"ADELANTO SOBRE SUELDOS\",\n          \"CurrencyId\": 0\n        },\n        \"Term\": 0,\n        \"BranchId\": 1,\n        \"OriginalAmount\": 151952,\n        \"NumberOfInstallments\": 0,\n        \"InstallmentPeriodicity\": 30,\n        \"TotalPaidInstallments\": 0,\n        \"InstallmentValue\": 15071,\n        \"StatusDescription\": \"Normal\",\n        \"AccountBalance\": -100000,\n        \"ValueDate\": \"2025-07-08\",\n        \"StatusId\": 0,\n        \"LoanGUID\": \"1766f6a9-c7e9-4ecf-8ae5-8202ad150377\",\n        \"InterestRate\": 20,\n        \"BranchDescription\": \"Sucursal Beta\"\n      },\n      {\n        \"AmortizationTypeDescription\": \"AMORTIZABLE FRANCÉS (CONSTANTE TOTAL)\",\n        \"AmortizationTypeId\": 3,\n        \"Product\": {\n          \"ProductGUID\": \"cc2dc934-3de1-47c1-bf67-be92cc3ea16e\",\n          \"CurrencyDescription\": \"Pesos Uruguayos\",\n          \"KindDescription\": \"Billete\",\n          \"CurrencySign\": \"$\",\n          \"KindId\": 0,\n          \"ProductDescription\": \"ADELANTO SOBRE SUELDOS\",\n          \"CurrencyId\": 0\n        },\n        \"Term\": 364,\n        \"BranchId\": 1,\n        \"OriginalAmount\": 122013,\n        \"NumberOfInstallments\": 12,\n        \"InstallmentPeriodicity\": 30,\n        \"TotalPaidInstallments\": 0,\n        \"InstallmentValue\": 12366,\n        \"ExpirationDate\": \"2026-07-12\",\n        \"StatusDescription\": \"Normal\",\n        \"AccountBalance\": -100000,\n        \"ValueDate\": \"2025-07-08\",\n        \"StatusId\": 0,\n        \"LoanGUID\": \"93faa6b6-360c-4204-89e4-318ce69d0533\",\n        \"InterestRate\": 20,\n        \"BranchDescription\": \"Sucursal Beta\"\n      },\n      {\n        \"AmortizationTypeDescription\": \"AMORTIZABLE FRANCÉS (CONSTANTE TOTAL)\",\n        \"AmortizationTypeId\": 3,\n        \"Product\": {\n          \"ProductGUID\": \"cc2dc934-3de1-47c1-bf67-be92cc3ea16e\",\n          \"CurrencyDescription\": \"Pesos Uruguayos\",\n          \"KindDescription\": \"Billete\",\n          \"CurrencySign\": \"$\",\n          \"KindId\": 0,\n          \"ProductDescription\": \"ADELANTO SOBRE SUELDOS\",\n          \"CurrencyId\": 0\n        },\n        \"Term\": 372,\n        \"BranchId\": 1,\n        \"OriginalAmount\": 135000,\n        \"NumberOfInstallments\": 12,\n        \"InstallmentPeriodicity\": 30,\n        \"TotalPaidInstallments\": 0,\n        \"InstallmentValue\": 14376,\n        \"ExpirationDate\": \"2026-02-12\",\n        \"StatusDescription\": \"Normal\",\n        \"AccountBalance\": -100000,\n        \"ValueDate\": \"2025-01-31\",\n        \"StatusId\": 0,\n        \"LoanGUID\": \"fdccf226-40f1-4fa2-8181-34fcb2849192\",\n        \"InterestRate\": 20,\n        \"BranchDescription\": \"Sucursal Beta\"\n      },\n      {\n        \"AmortizationTypeDescription\": \"AMORTIZABLE FRANCÉS (CONSTANTE TOTAL)\",\n        \"AmortizationTypeId\": 3,\n        \"Product\": {\n          \"ProductGUID\": \"cc2dc934-3de1-47c1-bf67-be92cc3ea16e\",\n          \"CurrencyDescription\": \"Pesos Uruguayos\",\n          \"KindDescription\": \"Billete\",\n          \"CurrencySign\": \"$\",\n          \"KindId\": 0,\n          \"ProductDescription\": \"ADELANTO SOBRE SUELDOS\",\n          \"CurrencyId\": 0\n        },\n        \"Term\": 372,\n        \"BranchId\": 1,\n        \"OriginalAmount\": 120000,\n        \"NumberOfInstallments\": 12,\n        \"InstallmentPeriodicity\": 30,\n        \"TotalPaidInstallments\": 0,\n        \"InstallmentValue\": 12915,\n        \"ExpirationDate\": \"2026-02-12\",\n        \"FirstUnpaidDate\": \"2025-03-12\",\n        \"StatusDescription\": \"Normal\",\n        \"AccountBalance\": -100000,\n        \"ValueDate\": \"2025-01-31\",\n        \"StatusId\": 0,\n        \"LoanGUID\": \"f0ff0277-fcf9-4f38-a89a-1d8c2003e131\",\n        \"InterestRate\": 20,\n        \"BranchDescription\": \"Sucursal Beta\"\n      },\n      {\n        \"AmortizationTypeDescription\": \"FLEXIBLE\",\n        \"AmortizationTypeId\": 6,\n        \"Product\": {\n          \"ProductGUID\": \"d4e7ea18-1292-48bf-b1af-13376ea7bb1c\",\n          \"CurrencyDescription\": \"Pesos Uruguayos\",\n          \"KindDescription\": \"Billete\",\n          \"CurrencySign\": \"$\",\n          \"KindId\": 0,\n          \"ProductDescription\": \"FLEXIBLE\",\n          \"CurrencyId\": 0\n        },\n        \"Term\": 360,\n        \"BranchId\": 1,\n        \"OriginalAmount\": 35000,\n        \"NumberOfInstallments\": 6,\n        \"InstallmentPeriodicity\": 30,\n        \"TotalPaidInstallments\": 0,\n        \"InstallmentValue\": 0,\n        \"ExpirationDate\": \"2026-04-30\",\n        \"FirstUnpaidDate\": \"2025-12-01\",\n        \"StatusDescription\": \"Normal\",\n        \"AccountBalance\": -100000,\n        \"ValueDate\": \"2025-11-01\",\n        \"StatusId\": 0,\n        \"LoanGUID\": \"2f7e42b0-1a78-4176-aa36-e16736e76db3\",\n        \"InterestRate\": 50,\n        \"BranchDescription\": \"Sucursal Beta\"\n      },\n      {\n        \"AmortizationTypeDescription\": \"FLEXIBLE\",\n        \"AmortizationTypeId\": 6,\n        \"Product\": {\n          \"ProductGUID\": \"d4e7ea18-1292-48bf-b1af-13376ea7bb1c\",\n          \"CurrencyDescription\": \"Pesos Uruguayos\",\n          \"KindDescription\": \"Billete\",\n          \"CurrencySign\": \"$\",\n          \"KindId\": 0,\n          \"ProductDescription\": \"FLEXIBLE\",\n          \"CurrencyId\": 0\n        },\n        \"Term\": 608,\n        \"BranchId\": 1,\n        \"OriginalAmount\": 15000,\n        \"NumberOfInstallments\": 10,\n        \"InstallmentPeriodicity\": 30,\n        \"TotalPaidInstallments\": 0,\n        \"InstallmentValue\": 0,\n        \"ExpirationDate\": \"2026-09-01\",\n        \"FirstUnpaidDate\": \"2025-12-01\",\n        \"StatusDescription\": \"Normal\",\n        \"AccountBalance\": -100000,\n        \"ValueDate\": \"2025-11-01\",\n        \"StatusId\": 0,\n        \"LoanGUID\": \"da0fcba1-fe81-41d9-bcbf-38bacb11d610\",\n        \"InterestRate\": 50,\n        \"BranchDescription\": \"Sucursal Beta\"\n      },\n      {\n        \"AmortizationTypeDescription\": \"AMORTIZABLE FRANCÉS (CONSTANTE TOTAL)\",\n        \"AmortizationTypeId\": 3,\n        \"Product\": {\n          \"ProductGUID\": \"cc2dc934-3de1-47c1-bf67-be92cc3ea16e\",\n          \"CurrencyDescription\": \"Pesos Uruguayos\",\n          \"KindDescription\": \"Billete\",\n          \"CurrencySign\": \"$\",\n          \"KindId\": 0,\n          \"ProductDescription\": \"ADELANTO SOBRE SUELDOS\",\n          \"CurrencyId\": 0\n        },\n        \"Term\": 360,\n        \"BranchId\": 1,\n        \"OriginalAmount\": 100000,\n        \"NumberOfInstallments\": 12,\n        \"InstallmentPeriodicity\": 30,\n        \"TotalPaidInstallments\": 0,\n        \"InstallmentValue\": 11924,\n        \"ExpirationDate\": \"2026-11-03\",\n        \"FirstUnpaidDate\": \"2025-12-03\",\n        \"StatusDescription\": \"Normal\",\n        \"AccountBalance\": -100000,\n        \"ValueDate\": \"2025-11-03\",\n        \"StatusId\": 0,\n        \"LoanGUID\": \"34c58bac-a09f-4708-9385-577d104d361c\",\n        \"InterestRate\": 65,\n        \"BranchDescription\": \"Sucursal Beta\"\n      },\n      {\n        \"AmortizationTypeDescription\": \"FLEXIBLE\",\n        \"AmortizationTypeId\": 6,\n        \"Product\": {\n          \"ProductGUID\": \"d4e7ea18-1292-48bf-b1af-13376ea7bb1c\",\n          \"CurrencyDescription\": \"Pesos Uruguayos\",\n          \"KindDescription\": \"Billete\",\n          \"CurrencySign\": \"$\",\n          \"KindId\": 0,\n          \"ProductDescription\": \"FLEXIBLE\",\n          \"CurrencyId\": 0\n        },\n        \"Term\": 300,\n        \"BranchId\": 1,\n        \"OriginalAmount\": 50000,\n        \"NumberOfInstallments\": 10,\n        \"InstallmentPeriodicity\": 30,\n        \"TotalPaidInstallments\": 0,\n        \"InstallmentValue\": 0,\n        \"ExpirationDate\": \"2027-12-26\",\n        \"FirstUnpaidDate\": \"2027-03-26\",\n        \"StatusDescription\": \"Normal\",\n        \"AccountBalance\": -100000,\n        \"ValueDate\": \"2027-02-26\",\n        \"StatusId\": 0,\n        \"LoanGUID\": \"282dc866-872c-428e-8f01-cdcc3c41b255\",\n        \"InterestRate\": 50,\n        \"BranchDescription\": \"Sucursal Beta\"\n      },\n      {\n        \"AmortizationTypeDescription\": \"AMORTIZABLE FRANCÉS (CONSTANTE TOTAL)\",\n        \"AmortizationTypeId\": 3,\n        \"Product\": {\n          \"ProductGUID\": \"cc2dc934-3de1-47c1-bf67-be92cc3ea16e\",\n          \"CurrencyDescription\": \"Pesos Uruguayos\",\n          \"KindDescription\": \"Billete\",\n          \"CurrencySign\": \"$\",\n          \"KindId\": 0,\n          \"ProductDescription\": \"ADELANTO SOBRE SUELDOS\",\n          \"CurrencyId\": 0\n        },\n        \"Term\": 630,\n        \"BranchId\": 1,\n        \"OriginalAmount\": 100000,\n        \"NumberOfInstallments\": 21,\n        \"InstallmentPeriodicity\": 30,\n        \"TotalPaidInstallments\": 0,\n        \"InstallmentValue\": 8308,\n        \"ExpirationDate\": \"2028-12-31\",\n        \"FirstUnpaidDate\": \"2027-08-01\",\n        \"StatusDescription\": \"Normal\",\n        \"AccountBalance\": -100000,\n        \"ValueDate\": \"2027-03-31\",\n        \"StatusId\": 0,\n        \"LoanGUID\": \"18ad145f-c779-4213-a92d-60b45e9ceabe\",\n        \"InterestRate\": 60,\n        \"BranchDescription\": \"Sucursal Beta\"\n      },\n      {\n        \"AmortizationTypeDescription\": \"AMORTIZABLE FRANCÉS (CONSTANTE TOTAL)\",\n        \"AmortizationTypeId\": 3,\n        \"Product\": {\n          \"ProductGUID\": \"204db26d-f2f0-453e-b167-2b8496fc6cca\",\n          \"CurrencyDescription\": \"Pesos Uruguayos\",\n          \"KindDescription\": \"Billete\",\n          \"CurrencySign\": \"$\",\n          \"KindId\": 0,\n          \"ProductDescription\": \"PRÉSTAMO PERSONAL\",\n          \"CurrencyId\": 0\n        },\n        \"Term\": 214,\n        \"BranchId\": 1,\n        \"OriginalAmount\": 1000,\n        \"NumberOfInstallments\": 7,\n        \"InstallmentPeriodicity\": 30,\n        \"TotalPaidInstallments\": 0,\n        \"InstallmentValue\": 1393,\n        \"ExpirationDate\": \"2028-01-12\",\n        \"FirstUnpaidDate\": \"2027-07-12\",\n        \"StatusDescription\": \"Normal\",\n        \"AccountBalance\": -100000,\n        \"ValueDate\": \"2027-06-12\",\n        \"StatusId\": 0,\n        \"LoanGUID\": \"6dac0e4a-d922-4c66-be3d-b75a7e72aa67\",\n        \"InterestRate\": 20,\n        \"BranchDescription\": \"Sucursal Beta\"\n      },\n      {\n        \"AmortizationTypeDescription\": \"AMORTIZABLE FRANCÉS (CONSTANTE TOTAL)\",\n        \"AmortizationTypeId\": 3,\n        \"Product\": {\n          \"ProductGUID\": \"2513af07-a65c-4454-b907-855940e08727\",\n          \"CurrencyDescription\": \"DÓLAR ESTADOUNIDENSE - BILLETE\",\n          \"KindDescription\": \"Billete\",\n          \"CurrencySign\": \"U$D\",\n          \"KindId\": 0,\n          \"ProductDescription\": \"PRÉSTAMO PERSONAL\",\n          \"CurrencyId\": 2225\n        },\n        \"Term\": 394,\n        \"BranchId\": 1,\n        \"OriginalAmount\": 1000,\n        \"NumberOfInstallments\": 12,\n        \"InstallmentPeriodicity\": 30,\n        \"TotalPaidInstallments\": 0,\n        \"InstallmentValue\": 208,\n        \"ExpirationDate\": \"2028-07-12\",\n        \"FirstUnpaidDate\": \"2027-08-12\",\n        \"StatusDescription\": \"Normal\",\n        \"AccountBalance\": -100000,\n        \"ValueDate\": \"2027-06-14\",\n        \"StatusId\": 0,\n        \"LoanGUID\": \"86c79e9c-4d46-4125-8c41-87c5d6384828\",\n        \"InterestRate\": 20,\n        \"BranchDescription\": \"Sucursal Beta\"\n      },\n      {\n        \"AmortizationTypeDescription\": \"AMORTIZABLE FRANCÉS (CONSTANTE TOTAL)\",\n        \"AmortizationTypeId\": 3,\n        \"Product\": {\n          \"ProductGUID\": \"cc2dc934-3de1-47c1-bf67-be92cc3ea16e\",\n          \"CurrencyDescription\": \"Pesos Uruguayos\",\n          \"KindDescription\": \"Billete\",\n          \"CurrencySign\": \"$\",\n          \"KindId\": 0,\n          \"ProductDescription\": \"ADELANTO SOBRE SUELDOS\",\n          \"CurrencyId\": 0\n        },\n        \"Term\": 360,\n        \"BranchId\": 90,\n        \"OriginalAmount\": 101680,\n        \"NumberOfInstallments\": 12,\n        \"InstallmentPeriodicity\": 30,\n        \"TotalPaidInstallments\": 0,\n        \"InstallmentValue\": 11587,\n        \"ExpirationDate\": \"2028-07-15\",\n        \"FirstUnpaidDate\": \"2027-09-15\",\n        \"StatusDescription\": \"Normal\",\n        \"AccountBalance\": -100000,\n        \"StatusId\": 0,\n        \"LoanGUID\": \"a10f0422-09ce-4015-a95b-cb4a8a98b6d8\",\n        \"InterestRate\": 57.5,\n        \"BranchDescription\": \"TESORERIA\"\n      },\n      {\n        \"AmortizationTypeDescription\": \"AMORTIZABLE FRANCÉS (CONSTANTE TOTAL)\",\n        \"AmortizationTypeId\": 3,\n        \"Product\": {\n          \"ProductGUID\": \"f78f8edd-f2dd-473c-a20f-bc6416ec85e7\",\n          \"CurrencyDescription\": \"Pesos Uruguayos\",\n          \"KindDescription\": \"Billete\",\n          \"CurrencySign\": \"$\",\n          \"KindId\": 0,\n          \"ProductDescription\": \"PRUEBA FACUNDO\",\n          \"CurrencyId\": 0\n        },\n        \"Term\": 364,\n        \"BranchId\": 1000,\n        \"OriginalAmount\": 1000,\n        \"NumberOfInstallments\": 12,\n        \"InstallmentPeriodicity\": 30,\n        \"TotalPaidInstallments\": 0,\n        \"InstallmentValue\": 303,\n        \"ExpirationDate\": \"2026-01-12\",\n        \"FirstUnpaidDate\": \"2025-02-12\",\n        \"StatusDescription\": \"Normal\",\n        \"AccountBalance\": -100000,\n        \"ValueDate\": \"2025-01-08\",\n        \"StatusId\": 0,\n        \"LoanGUID\": \"51b4f3d7-2976-4e1a-bb03-545ad05e219e\",\n        \"InterestRate\": 20,\n        \"BranchDescription\": \"Sucursa demo\"\n      },\n      {\n        \"AmortizationTypeDescription\": \"AMORTIZABLE FRANCÉS (CONSTANTE TOTAL)\",\n        \"AmortizationTypeId\": 3,\n        \"Product\": {\n          \"ProductGUID\": \"f78f8edd-f2dd-473c-a20f-bc6416ec85e7\",\n          \"CurrencyDescription\": \"Pesos Uruguayos\",\n          \"KindDescription\": \"Billete\",\n          \"CurrencySign\": \"$\",\n          \"KindId\": 0,\n          \"ProductDescription\": \"PRUEBA FACUNDO\",\n          \"CurrencyId\": 0\n        },\n        \"Term\": 364,\n        \"BranchId\": 1000,\n        \"OriginalAmount\": 1000,\n        \"NumberOfInstallments\": 12,\n        \"InstallmentPeriodicity\": 30,\n        \"TotalPaidInstallments\": 0,\n        \"InstallmentValue\": 303,\n        \"ExpirationDate\": \"2026-01-12\",\n        \"FirstUnpaidDate\": \"2025-03-12\",\n        \"StatusDescription\": \"Normal\",\n        \"AccountBalance\": -100000,\n        \"ValueDate\": \"2025-01-08\",\n        \"StatusId\": 0,\n        \"LoanGUID\": \"de747bbb-8596-4b84-9cd4-7e4663a22a24\",\n        \"InterestRate\": 20,\n        \"BranchDescription\": \"Sucursa demo\"\n      },\n      {\n        \"AmortizationTypeDescription\": \"AMORTIZABLE FRANCÉS (CONSTANTE TOTAL)\",\n        \"AmortizationTypeId\": 3,\n        \"Product\": {\n          \"ProductGUID\": \"bf0d7e10-dce6-4bd4-b866-9984556613ec\",\n          \"CurrencyDescription\": \"Pesos Uruguayos\",\n          \"KindDescription\": \"Billete\",\n          \"CurrencySign\": \"$\",\n          \"KindId\": 0,\n          \"ProductDescription\": \"GRUPALES\",\n          \"CurrencyId\": 0\n        },\n        \"Term\": 110,\n        \"BranchId\": 1,\n        \"OriginalAmount\": 12600,\n        \"NumberOfInstallments\": 16,\n        \"InstallmentPeriodicity\": 7,\n        \"TotalPaidInstallments\": 0,\n        \"InstallmentValue\": 1309,\n        \"ExpirationDate\": \"2027-10-30\",\n        \"FirstUnpaidDate\": \"2027-07-17\",\n        \"StatusDescription\": \"Normal\",\n        \"AccountBalance\": -100000,\n        \"ValueDate\": \"2027-07-10\",\n        \"StatusId\": 0,\n        \"LoanGUID\": \"d1320758-1d85-4a3d-ae62-30d44165691d\",\n        \"InterestRate\": 18.5,\n        \"BranchDescription\": \"Sucursal Beta\"\n      },\n      {\n        \"AmortizationTypeDescription\": \"AMORTIZABLE FRANCÉS (CONSTANTE TOTAL)\",\n        \"AmortizationTypeId\": 3,\n        \"Product\": {\n          \"ProductGUID\": \"bf0d7e10-dce6-4bd4-b866-9984556613ec\",\n          \"CurrencyDescription\": \"Pesos Uruguayos\",\n          \"KindDescription\": \"Billete\",\n          \"CurrencySign\": \"$\",\n          \"KindId\": 0,\n          \"ProductDescription\": \"GRUPALES\",\n          \"CurrencyId\": 0\n        },\n        \"Term\": 111,\n        \"BranchId\": 1,\n        \"OriginalAmount\": 10000,\n        \"NumberOfInstallments\": 16,\n        \"InstallmentPeriodicity\": 7,\n        \"TotalPaidInstallments\": 0,\n        \"InstallmentValue\": 659,\n        \"ExpirationDate\": \"2028-03-22\",\n        \"FirstUnpaidDate\": \"2027-12-08\",\n        \"StatusDescription\": \"Normal\",\n        \"AccountBalance\": -100000,\n        \"ValueDate\": \"2027-12-01\",\n        \"StatusId\": 0,\n        \"LoanGUID\": \"ba5c739b-2a47-4010-b72f-c995985e6da7\",\n        \"InterestRate\": 7,\n        \"BranchDescription\": \"Sucursal Beta\"\n      },\n      {\n        \"AmortizationTypeDescription\": \"AMORTIZABLE FRANCÉS (CONSTANTE TOTAL)\",\n        \"AmortizationTypeId\": 3,\n        \"Product\": {\n          \"ProductGUID\": \"bf0d7e10-dce6-4bd4-b866-9984556613ec\",\n          \"CurrencyDescription\": \"Pesos Uruguayos\",\n          \"KindDescription\": \"Billete\",\n          \"CurrencySign\": \"$\",\n          \"KindId\": 0,\n          \"ProductDescription\": \"GRUPALES\",\n          \"CurrencyId\": 0\n        },\n        \"Term\": 83,\n        \"BranchId\": 91,\n        \"OriginalAmount\": 30000,\n        \"NumberOfInstallments\": 12,\n        \"InstallmentPeriodicity\": 7,\n        \"TotalPaidInstallments\": 0,\n        \"InstallmentValue\": 3127,\n        \"ExpirationDate\": \"2027-07-06\",\n        \"FirstUnpaidDate\": \"2027-04-20\",\n        \"StatusDescription\": \"Normal\",\n        \"AccountBalance\": -100000,\n        \"ValueDate\": \"2027-04-13\",\n        \"StatusId\": 0,\n        \"LoanGUID\": \"765fb997-7172-4931-b7be-3623f6bc5e58\",\n        \"InterestRate\": 15,\n        \"BranchDescription\": \"TESORERIA BONOS\"\n      }\n    ],\n    \"AccountBalance\": \"\",\n    \"AmortizationTypeId\": 0,\n    \"AmortizationTypeDescription\": \"\",\n    \"BranchId\": 0,\n    \"BranchDescription\": \"\",\n    \"DateOfLastTotalPayment\": \"\",\n    \"ExpirationDate\": \"\",\n    \"FirstUnpaidDate\": \"\",\n    \"InstallmentPeriodicity\": 0,\n    \"InstallmentValue\": 0,\n    \"InterestRate\": 0,\n    \"LoanGUID\": \"\",\n    \"NumberOfInstallments\": 0,\n    \"OriginalAmount\": 0,\n    \"Product\": {\n      \"CurrencyId\": \"\",\n      \"CurrencyDescription\": \"\",\n      \"CurrencySign\": \"\",\n      \"KindId\": 0,\n      \"KindDescription\": \"\",\n      \"ProductDescription\": \"\",\n      \"ProductGUId\": \"\"\n    },\n    \"StatusId\": 0,\n    \"StatusDescription\": \"\",\n    \"Term\": 0,\n    \"TotalPaidInstallments\": 0,\n    \"ValueDate\": \"\"\n  },\n  \"BusinessErrors\": \"\",\n  \"Btoutreq\": {\n    \"Estado\": \"OK\",\n    \"Fecha\": \"2026-01-01\",\n    \"Hora\": \"00:00:00\",\n    \"Numero\": \"00000000\",\n    \"Servicio\": \"PublicLoans.getCustomerLoans\",\n    \"Requerimiento\": \"1\",\n    \"Canal\": \"BTDIGITAL\"\n  }\n}"
        }
      ]
    }
  },
  "structuredTypes": [
    {
      "typeName": "SdtsBTLOWCustomerLoan",
      "fields": [
        {
          "Nombre": "AccountBalance",
          "Tipo": "Double <strong>(Length: 18)</strong>",
          "Comentarios": "Saldo contable."
        },
        {
          "Nombre": "AmortizationTypeId",
          "Tipo": "Byte",
          "Comentarios": "Identificador del tipo de amortización."
        },
        {
          "Nombre": "AmortizationTypeDescription",
          "Tipo": "String",
          "Comentarios": "Descripción del tipo de amortización."
        },
        {
          "Nombre": "BranchId",
          "Tipo": "Int",
          "Comentarios": "Identificador de sucursal."
        },
        {
          "Nombre": "BranchDescription",
          "Tipo": "String",
          "Comentarios": "Descripción de sucursal."
        },
        {
          "Nombre": "DateOfLastTotalPayment",
          "Tipo": "Date",
          "Comentarios": "Fecha del último pago total."
        },
        {
          "Nombre": "ExpirationDate",
          "Tipo": "Date",
          "Comentarios": "Fecha de vencimiento."
        },
        {
          "Nombre": "FirstUnpaidDate",
          "Tipo": "Date",
          "Comentarios": "Fecha del primer impago."
        },
        {
          "Nombre": "InstallmentPeriodicity",
          "Tipo": "Int",
          "Comentarios": "Periodicidad de cuotas."
        },
        {
          "Nombre": "InstallmentValue",
          "Tipo": "Double",
          "Comentarios": "Valor de la cuota."
        },
        {
          "Nombre": "InterestRate",
          "Tipo": "Double",
          "Comentarios": "Tasa de interés."
        },
        {
          "Nombre": "LoanGUID",
          "Tipo": "String",
          "Comentarios": "GUID (identificador único global) del préstamo."
        },
        {
          "Nombre": "NumberOfInstallments",
          "Tipo": "Int",
          "Comentarios": "Número de cuotas."
        },
        {
          "Nombre": "OriginalAmount",
          "Tipo": "Double",
          "Comentarios": "Monto original."
        },
        {
          "Nombre": "Product",
          "Tipo": "<a href=\"#sdtsbtphwproduct\">SdtsBTPHWProduct</a>",
          "Comentarios": "Producto."
        },
        {
          "Nombre": "StatusId",
          "Tipo": "Short",
          "Comentarios": "Identificador de estado."
        },
        {
          "Nombre": "StatusDescription",
          "Tipo": "String",
          "Comentarios": "Descripción del estado."
        },
        {
          "Nombre": "Term",
          "Tipo": "Int",
          "Comentarios": "Plazo."
        },
        {
          "Nombre": "TotalPaidInstallments",
          "Tipo": "Int",
          "Comentarios": "Total de cuotas pagadas."
        },
        {
          "Nombre": "ValueDate",
          "Tipo": "Date",
          "Comentarios": "Fecha valor."
        }
      ]
    },
    {
      "typeName": "SdtsBTPHWProduct",
      "fields": [
        {
          "Nombre": "CurrencyId",
          "Tipo": "Short <strong>(Length: 4)</strong>",
          "Comentarios": "Identificador de moneda."
        },
        {
          "Nombre": "CurrencyDescription",
          "Tipo": "String <strong>(Length: 30)</strong>",
          "Comentarios": "Descripción de moneda."
        },
        {
          "Nombre": "CurrencySign",
          "Tipo": "String <strong>(Length: 5)</strong>",
          "Comentarios": "Signo de moneda."
        },
        {
          "Nombre": "KindId",
          "Tipo": "Int",
          "Comentarios": "Identificador del tipo."
        },
        {
          "Nombre": "KindDescription",
          "Tipo": "String",
          "Comentarios": "Descripción del tipo."
        },
        {
          "Nombre": "ProductDescription",
          "Tipo": "String",
          "Comentarios": "Descripción del producto."
        },
        {
          "Nombre": "ProductGUId",
          "Tipo": "String",
          "Comentarios": "Identificador único global (GUID) del producto."
        }
      ]
    }
  ],
  "valuesTable": []
}