{
  "slug": "personas/obtener/obtenerdomicilios",
  "pageTitle": "Obtener Domicilios",
  "description": "Método para obtener un listado de los domicilios de una persona.",
  "pubName": "BTPersonas.ObtenerDomicilios",
  "programa": "RBTPG197",
  "scope": "Global",
  "hasBackendConfig": false,
  "backendText": "",
  "backendData": [],
  "inputData": [
    {
      "Nombre": "personaUId",
      "Tipo": "Long",
      "Comentarios": "Identificador único de persona."
    }
  ],
  "outputData": [
    {
      "Nombre": "sdtDomicilios",
      "Tipo": "<a href=\"#sbtdomicilio1\">sBTDomicilio1</a>",
      "Comentarios": "Listado de domicilios."
    }
  ],
  "errors": [
    {
      "Código": "30001",
      "Descripción": "No se recibió el identificador de la persona."
    },
    {
      "Código": "30002",
      "Descripción": "El identificador de la persona no es correcto."
    },
    {
      "Código": "30011",
      "Descripción": "No se encontraron domicilios para la persona."
    }
  ],
  "errorsNote": "",
  "examples": {
    "invocation": {
      "xml": "<soapenv:Envelope xmlns:soapenv=\"http://schemas.xmlsoap.org/soap/envelope/\" xmlns:bts=\"http://uy.com.dlya.bantotal/BTSOA/\">\n   <soapenv:Header/>\n   <soapenv:Body>\n      <bts:BTPersonas.ObtenerDomicilios>\n         <bts:Btinreq>\n            <bts:Device>10.12.10.159</bts:Device>\n            <bts:Usuario>MINSTALADOR</bts:Usuario>\n            <bts:Requerimiento>1</bts:Requerimiento>\n            <bts:Canal>BTDIGITAL</bts:Canal>\n            <bts:Token>772a871c734A8B5C60A82434</bts:Token>\n         </bts:Btinreq>\n         <bts:personaUId>101</bts:personaUId>\n      </bts:BTPersonas.ObtenerDomicilios>\n   </soapenv:Body>\n</soapenv:Envelope>",
      "json": "curl -X POST \\\n  'http://btd-bantotal.eastus2.cloudapp.azure.com:4462/btdeveloper/servlet/com.dlya.bantotal.odwsbt_BTPersonas_v1?ObtenerDomicilios=' \\\n  -H 'cache-control: no-cache' \\\n  -H 'content-type: application/json' \\\n  -H 'postman-token: a12f013d-9875-6451-dd62-ad7bb0217b5c' \\\n  -d '{\n\t\"Btinreq\": {\n\t\t\"Device\": \"AV\",\n\t\t\"Usuario\": \"MINSTALADOR\",\n\t\t\"Requerimiento\": \"\",\n\t\t\"Canal\": \"BTDIGITAL\",\n\t\t\"Token\": \"fa2c02c95a4A8B5C60A82434\"\n\t},\n    \"personaUId\": \"101\"\n}'"
    },
    "response": {
      "xml": "<SOAP-ENV:Envelope xmlns:SOAP-ENV=\"http://schemas.xmlsoap.org/soap/envelope/\" xmlns:xsd=\"http://www.w3.org/2001/XMLSchema\" xmlns:SOAP-ENC=\"http://schemas.xmlsoap.org/soap/encoding/\" xmlns:xsi=\"http://www.w3.org/2001/XMLSchema-instance\" xmlns:bts=\"http://uy.com.dlya.bantotal/BTSOA/\">\n   <SOAP-ENV:Body>\n      <BTPersonas.ObtenerDomiciliosResponse xmlns=\"http://uy.com.dlya.bantotal/BTSOA/\">\n         <Btinreq>\n            <Device>10.12.10.159</Device>\n            <Usuario>MINSTALADOR</Usuario>\n            <Requerimiento>1</Requerimiento>\n            <Canal>BTDIGITAL</Canal>\n            <Token>772a871c734A8B5C60A82434</Token>\n         </Btinreq>\n         <sdtDomicilios>\n            <sBTDomicilio1>\n               <paisDomicilioId>845</paisDomicilioId>\n               <paisDomicilio>URUGUAY</paisDomicilio>\n               <departamentoId>4</departamentoId>\n               <departamento>Colonia</departamento>\n               <localidadId>1357</localidadId>\n               <localidad>Riachuelo</localidad>\n               <barrioId>0</barrioId>\n               <barrio/>\n               <calle>1</calle>\n               <numeroPuerta>167</numeroPuerta>\n               <apartamento/>\n               <codigoPostal/>\n               <tipoDeDomicilioId>1</tipoDeDomicilioId>\n               <tipoDeDomicilio>Residencia</tipoDeDomicilio>\n               <direccion>CALLE 1 NRO 167</direccion>\n               <referencia>Casa Azul</referencia>\n            </sBTDomicilio1>\n         </sdtDomicilios>\n         <Erroresnegocio></Erroresnegocio>\n         <Btoutreq>\n            <Numero>2991</Numero>\n            <Estado>OK</Estado>\n            <Servicio>BTPersonas.ObtenerDomicilios</Servicio>\n            <Requerimiento>1</Requerimiento>\n            <Fecha>2018-11-08</Fecha>\n            <Hora>16:05:36</Hora>\n            <Canal>BTDIGITAL</Canal>\n         </Btoutreq>\n      </BTPersonas.ObtenerDomiciliosResponse>\n   </SOAP-ENV:Body>\n</SOAP-ENV:Envelope>",
      "json": "'{\n\t\"Btinreq\": {\n\t\t\"Device\": \"AV\",\n\t\t\"Usuario\": \"MINSTALADOR\",\n\t\t\"Requerimiento\": \"\",\n\t\t\"Canal\": \"BTDIGITAL\",\n\t\t\"Token\": \"fa2c02c95a4A8B5C60A82434\"\n\t},\n    \"sdtDomicilios\": {\n        \"sBTDomicilio1\": [\n            {\n                \"localidad\": \"Riachuelo\",\n                \"paisDomicilio\": \"URUGUAY\",\n                \"barrioId\": \"0\",\n                \"departamento\": \"Colonia\",\n                \"numeroPuerta\": \"167\",\n                \"barrio\": \"\",\n                \"localidadId\": \"1357\",\n                \"tipoDeDomicilioId\": \"1\",\n                \"codigoPostal\": \"\",\n                \"calle\": \"1\",\n                \"apartamento\": \"\",\n                \"tipoDeDomicilio\": \"Residencia\",\n                \"departamentoId\": \"4\",\n                \"paisDomicilioId\": \"845\"\n            }\n        ]\n    },\n    \"Erroresnegocio\": {\n        \"BTErrorNegocio\": []\n    },\n    \"Btoutreq\": {\n        \"Numero\": \"2993\",\n        \"Estado\": \"OK\",\n        \"Servicio\": \"BTPersonas.ObtenerDomicilios\",\n        \"Requerimiento\": \"1\",\n        \"Fecha\": \"2018-11-08\",\n        \"Hora\": \"16:07:57\",\n        \"Canal\": \"BTDIGITAL\"\n    }\n}'"
    }
  },
  "structuredTypes": [
    {
      "typeName": "sBTDomicilio1",
      "fields": [
        {
          "Nombre": "apartamento",
          "Tipo": "String",
          "Comentarios": "Número de apartamento."
        },
        {
          "Nombre": "barrio",
          "Tipo": "String",
          "Comentarios": "Nombre del barrio."
        },
        {
          "Nombre": "barrioId",
          "Tipo": "Int",
          "Comentarios": "Identificador del barrio."
        },
        {
          "Nombre": "calle",
          "Tipo": "String",
          "Comentarios": "Calle del domicilio."
        },
        {
          "Nombre": "codigoPostal",
          "Tipo": "String",
          "Comentarios": "Código postal."
        },
        {
          "Nombre": "departamento",
          "Tipo": "String",
          "Comentarios": "Nombre del departamento."
        },
        {
          "Nombre": "departamentoId",
          "Tipo": "Int",
          "Comentarios": "Identificador del departamento."
        },
        {
          "Nombre": "dirección",
          "Tipo": "String",
          "Comentarios": "Dirección."
        },
        {
          "Nombre": "localidad",
          "Tipo": "String",
          "Comentarios": "Nombre de la localidad."
        },
        {
          "Nombre": "localidadId",
          "Tipo": "Int",
          "Comentarios": "Identificador de la localidad."
        },
        {
          "Nombre": "numeroPuerta",
          "Tipo": "String",
          "Comentarios": "Número de puerta."
        },
        {
          "Nombre": "paisDomicilio",
          "Tipo": "String",
          "Comentarios": "Nombre del país."
        },
        {
          "Nombre": "paisDomicilioId",
          "Tipo": "Short",
          "Comentarios": "Identificador del país."
        },
        {
          "Nombre": "referencia",
          "Tipo": "String",
          "Comentarios": "Referencia."
        },
        {
          "Nombre": "tipoDeDomicilio",
          "Tipo": "String",
          "Comentarios": "Nombre del tipo de domicilio."
        },
        {
          "Nombre": "tipoDeDomicilioId",
          "Tipo": "Short",
          "Comentarios": "Identificador del tipo de domicilio."
        }
      ]
    }
  ],
  "valuesTable": []
}