{
  "slug": "prestamos/pagar/adelantarcapitalconreducciondecuota",
  "pageTitle": "Adelantar Capital Con Reducción De Cuota",
  "description": "Método para realizar el pago de cuota de un préstamo con adelanto de capital.",
  "pubName": "BTPrestamos.AdelantarCapitalConReduccionDeCuota",
  "programa": "RBTPG555",
  "scope": "Global",
  "hasBackendConfig": false,
  "backendText": "",
  "backendData": [],
  "inputData": [
    {
      "Nombre": "operacionUId",
      "Tipo": "Long",
      "Comentarios": "Identificador único de la operación."
    },
    {
      "Nombre": "clienteUId",
      "Tipo": "Long",
      "Comentarios": "Identificador único del cliente."
    },
    {
      "Nombre": "importe",
      "Tipo": "Double",
      "Comentarios": "Importe."
    },
    {
      "Nombre": "operacionUId_Cobro",
      "Tipo": "Long",
      "Comentarios": "Identificador único de la operación de cobro."
    },
    {
      "Nombre": "referencia",
      "Tipo": "String",
      "Comentarios": "Referencia."
    },
    {
      "Nombre": "modo",
      "Tipo": "String",
      "Comentarios": "[Hidden: Valor fijo 'A' para este método]."
    },
    {
      "Nombre": "modalidadIntereses",
      "Tipo": "String",
      "Comentarios": "Modalidad de intereses. Se pueden enviar los siguientes <a href=\"#valores\">valores</a>."
    }
  ],
  "outputData": [
    {
      "Nombre": "movimientoUId",
      "Tipo": "Long",
      "Comentarios": "Identificador único del movimiento."
    }
  ],
  "errors": [
    {
      "Código": "30001",
      "Descripción": "No se recibió el identificador único de operación de préstamo."
    },
    {
      "Código": "30002",
      "Descripción": "No se recibió el identificador único de operación de cobro."
    },
    {
      "Código": "30003",
      "Descripción": "Debe ingresar importe."
    },
    {
      "Código": "30004",
      "Descripción": "No se recuperó la operación para el Identificador: [Número de Identificador]."
    },
    {
      "Código": "30005",
      "Descripción": "No se recuperó la operación para el Identificador: [Número de Identificador]."
    },
    {
      "Código": "30006",
      "Descripción": "No se recibió el identificador de cliente."
    },
    {
      "Código": "30007",
      "Descripción": "No se recuperó la cuenta para el Identificador de cliente: [Número de Identificador]."
    },
    {
      "Código": "30008",
      "Descripción": "El préstamo no pertenece al cliente."
    },
    {
      "Código": "30009",
      "Descripción": "La operación de cobro no pertenece al cliente."
    },
    {
      "Código": "30010",
      "Descripción": "No se ingresó la modalidad de intereses."
    },
    {
      "Código": "30011",
      "Descripción": "El valor del campo modalidadIntereses tiene que ser CP o SP."
    },
    {
      "Código": "30100",
      "Descripción": "Error en la contabilización."
    },
    {
      "Código": "51002",
      "Descripción": "La operación no existe."
    },
    {
      "Código": "51003",
      "Descripción": "La operación de cobro no existe."
    },
    {
      "Código": "51012",
      "Descripción": "La operación esta cancelada."
    },
    {
      "Código": "51013",
      "Descripción": "La operación de cobro esta cancelada."
    }
  ],
  "errorsNote": "",
  "examples": {
    "invocation": {
      "xml": "<soapenv:Envelope xmlns:soapenv=\"http://schemas.xmlsoap.org/soap/envelope/\" xmlns:bts=\"http://uy.com.dlya.bantotal/BTSOA/\">\r\n   <soapenv:Header/>\r\n   <soapenv:Body>\r\n      <bts:BTPrestamos.AdelantarCapitalConReduccionDeCuota>\r\n         <bts:Btinreq>\r\n            <bts:Requerimiento>0</bts:Requerimiento>\r\n            <bts:Canal>BTDIGITAL</bts:Canal>\r\n            <bts:Device>GZ</bts:Device>\r\n            <bts:Usuario>INSTALADOR</bts:Usuario>\r\n            <bts:Token>9436BF7CB5B5BB404CC6E5A7</bts:Token>\r\n         </bts:Btinreq>\r\n         <bts:operacionUId>212</bts:operacionUId>\r\n         <bts:clienteUId>61</bts:clienteUId>\r\n         <bts:importe>30</bts:importe>\r\n         <bts:operacionUId_Cobro>21</bts:operacionUId_Cobro>\r\n         <bts:referencia></bts:referencia>\r\n         <bts:modalidadIntereses>SP</bts:modalidadIntereses>\r\n      </bts:BTPrestamos.AdelantarCapitalConReduccionDeCuota>\r\n   </soapenv:Body>\r\n</soapenv:Envelope>",
      "json": "curl -X POST \\\r\n  'http://btd-bantotal.eastus2.cloudapp.azure.com:4462/btdeveloper/servlet/com.dlya.bantotal.odwsbt_BTPrestamos?AdelantarCapitalConReduccionDeCuota' \\\r\n  -H 'cache-control: no-cache' \\\r\n  -H 'content-type: application/json' \\\r\n  -H 'postman-token: 52baf1dc-e302-90a6-0de1-24fa234c0379' \\\r\n  -d '{\r\n    \"Btinreq\": {\r\n        \"Requerimiento\": 0,\r\n        \"Canal\": \"BTDIGITAL\",\r\n        \"Device\": \"GZ\",\r\n        \"Usuario\": \"INSTALADOR\",\r\n        \"Token\": \"9436BF7CB5B5BB404CC6E5A7\"\r\n    },\r\n    \"operacionUId\": 212,\r\n    \"clienteUId\": 61,\r\n    \"importe\": 30,\r\n    \"operacionUId_Cobro\": 21,\r\n    \"referencia\": \"\",\r\n    \"modalidadIntereses\": \"SP\"\r\n}'"
    },
    "response": {
      "xml": "<SOAP-ENV:Envelope xmlns:SOAP-ENV=\"http://schemas.xmlsoap.org/soap/envelope/\" xmlns:xsd=\"http://www.w3.org/2001/XMLSchema\" xmlns:SOAP-ENC=\"http://schemas.xmlsoap.org/soap/encoding/\" xmlns:xsi=\"http://www.w3.org/2001/XMLSchema-instance\">\r\n   <SOAP-ENV:Body>\r\n      <BTPrestamos.AdelantarCapitalConReduccionDeCuotaResponse xmlns=\"http://uy.com.dlya.bantotal/BTSOA/\">\r\n         <Btinreq>\r\n            <Device>GZ</Device>\r\n            <Usuario>INSTALADOR</Usuario>\r\n            <Requerimiento>0</Requerimiento>\r\n            <Canal>BTDIGITAL</Canal>\r\n            <Token>9436BF7CB5B5BB404CC6E5A7</Token>\r\n         </Btinreq>\r\n         <movimientoUId>66</movimientoUId>\r\n         <Erroresnegocio></Erroresnegocio>\r\n         <Btoutreq>\r\n            <Numero>20604</Numero>\r\n            <Estado>OK</Estado>\r\n            <Servicio>BTPrestamos.AdelantarCapitalConReduccionDeCuota</Servicio>\r\n            <Fecha>2024-05-21</Fecha>\r\n            <Requerimiento>0</Requerimiento>\r\n            <Hora>15:43:23</Hora>\r\n            <Canal>BTDIGITAL</Canal>\r\n         </Btoutreq>\r\n      </BTPrestamos.AdelantarCapitalConReduccionDeCuotaResponse>\r\n   </SOAP-ENV:Body>\r\n</SOAP-ENV:Envelope>",
      "json": "'{\r\n    \"Btinreq\": {\r\n        \"Device\": \"GZ\",\r\n        \"Usuario\": \"INSTALADOR\",\r\n        \"Requerimiento\": 0,\r\n        \"Canal\": \"BTDIGITAL\",\r\n        \"Token\": \"9436BF7CB5B5BB404CC6E5A7\"\r\n    },\r\n    \"movimientoUId\": 66,\r\n    \"Erroresnegocio\": {\r\n        \"BTErrorNegocio\": []\r\n    },\r\n    \"Btoutreq\": {\r\n        \"Numero\": 20604,\r\n        \"Estado\": \"OK\",\r\n        \"Servicio\": \"BTPrestamos.AdelantarCapitalConReduccionDeCuota\",\r\n        \"Fecha\": \"2024-05-21\",\r\n        \"Requerimiento\": 0,\r\n        \"Hora\": \"15:43:23\",\r\n        \"Canal\": \"BTDIGITAL\"\r\n    }\r\n}'"
    }
  },
  "structuredTypes": [],
  "valuesTable": [
    {
      "elementValName": "modalidadIntereses",
      "listHeader": "Valor,Comentarios",
      "fields": [
        {
          "Valor": "SP",
          "Comentarios": "Sin perdón."
        },
        {
          "Valor": "CP",
          "Comentarios": "Con perdón."
        }
      ],
      "description": "Este campo tiene dos opciones:"
    }
  ]
}